test.php/时序逻辑/状态机/fsm_3.v
module fsm (
    Clock,Reset,A,K2,K1
);
    input Clock,Reset,A;
    output K1,K2;
    reg K2,K1;
    reg [1:0] state,nextstate;
    parameter Idle = 2'b00,
              Start = 2'b01,
              Stop = 2'b10,
              Clear = 2'b11;
              //每一个时钟沿产生一次可能的状态变化
    always @(posedge Clock ) 
    begin
        if(!Reset)
            state<= Idle;
        else
            state<=nextstate;
    end
    //产生下一状态的组合逻辑
    always @(state or A) 
    begin
        case(state)
            Idle:if(A)
                                nextstate        = Start;
                        else    nextstate        = Idle;
                        Start  :if(!A) nextstate = Stop;
                        else    nextstate        = Start;
                        Stop   :if(A) nextstate  = Clear;
                        else    nextstate        = Stop;
                        Clear  :if(!A) nextstate = Idle;
                        else    nextstate        = Clear;
                        default:    nextstate    = 2'bxx;
        endcase
    end
    //产生输出K1的组合逻辑
    always @(state or Reset or A) 
    begin
    if(!Reset) K1=0;
        else
            if(state == Clear && !A) //从Clear转向Idle
                K1=1;
            else K1=0;    
    end
    //产生输出K2的组合逻辑
    always @(state or Reset or A)
    begin
        if(!Reset) K2=0;
        else
            if(state==Stop&&A)//从Stop转向Clear
                     K2 = 1;
                else K2 = 0;
    end
    endmodule

test.php/时序逻辑/状态机/fsm_tb.v
`include "/Users/craft/资料/verilog_study/test.php/时序逻辑/状态机/fsm_3.v"
`timescale 1ns/1ns
module test;
    reg a;
    reg clock,rst;
    wire k2,k1;
initial  
    begin
        a=0;
        rst=1;
        clock=0;
        #22 rst=0;
        #133 rst=1;
    end
always #50 clock = ~clock;
always @(posedge clock ) 
    begin
        #30 a={$random}%2;
        #(3*50+12);
    end
initial
begin            
    $dumpfile("fsm_3.vcd");        //生成的vcd文件名称
    $dumpvars(0, test);     //tb模块名称 0代表这个模块下所有波形 
end
initial 
    begin
    #1000000 $stop;
    end

fsm test(.Clock(clock),.Reset(rst),.A(a),.K2(k2),.K1(k1));
endmodule

test.php/时序逻辑/状态机/fsm_3.vcd
$date
	Fri Apr 23 17:49:34 2021
$end
$version
	Icarus Verilog
$end
$timescale
	1ns
$end
$scope module test $end
$scope module test $end
$var wire 1 ! A $end
$var wire 1 " Clock $end
$var wire 1 # Reset $end
$var reg 1 $ K1 $end
$var reg 1 % K2 $end
$var reg 2 & nextstate [1:0] $end
$var reg 2 ' state [1:0] $end
$upscope $end
$upscope $end
$enddefinitions $end
#0
$dumpvars
bx '
bx &
0%
0$
1#
0"
0!
$end
#22
0#
#50
b0 &
b0 '
1"
#100
0"
#150
1"
#155
1#
#200
0"
#250
1"
#280
b1 &
1!
#300
0"
#350
b1 '
1"
#400
0"
#450
1"
#500
0"
#550
1"
#600
0"
#650
1"
#700
0"
#750
1"
#800
0"
#850
1"
#900
0"
#950
1"
#1000
0"
#1050
1"
#1100
0"
#1150
1"
#1200
0"
#1250
1"
#1300
0"
#1350
1"
#1400
0"
#1450
1"
#1480
b10 &
0!
#1500
0"
#1550
b10 '
1"
#1600
0"
#1650
1"
#1680
1%
b11 &
1!
#1700
0"
#1750
0%
b11 '
1"
#1800
0"
#1850
1"
#1900
0"
#1950
1"
#2000
0"
#2050
1"
#2080
1$
b0 &
0!
#2100
0"
#2150
0$
b0 '
1"
#2200
0"
#2250
1"
#2280
b1 &
1!
#2300
0"
#2350
b1 '
1"
#2400
0"
#2450
1"
#2500
0"
#2550
1"
#2600
0"
#2650
1"
#2680
b10 &
0!
#2700
0"
#2750
b10 '
1"
#2800
0"
#2850
1"
#2880
1%
b11 &
1!
#2900
0"
#2950
0%
b11 '
1"
#3000
0"
#3050
1"
#3080
1$
b0 &
0!
#3100
0"
#3150
0$
b0 '
1"
#3200
0"
#3250
1"
#3280
b1 &
1!
#3300
0"
#3350
b1 '
1"
#3400
0"
#3450
1"
#3480
b10 &
0!
#3500
0"
#3550
b10 '
1"
#3600
0"
#3650
1"
#3680
1%
b11 &
1!
#3700
0"
#3750
0%
b11 '
1"
#3800
0"
#3850
1"
#3900
0"
#3950
1"
#4000
0"
#4050
1"
#4080
1$
b0 &
0!
#4100
0"
#4150
0$
b0 '
1"
#4200
0"
#4250
1"
#4280
b1 &
1!
#4300
0"
#4350
b1 '
1"
#4400
0"
#4450
1"
#4480
b10 &
0!
#4500
0"
#4550
b10 '
1"
#4600
0"
#4650
1"
#4700
0"
#4750
1"
#4800
0"
#4850
1"
#4900
0"
#4950
1"
#5000
0"
#5050
1"
#5080
1%
b11 &
1!
#5100
0"
#5150
0%
b11 '
1"
#5200
0"
#5250
1"
#5280
1$
b0 &
0!
#5300
0"
#5350
0$
b0 '
1"
#5400
0"
#5450
1"
#5480
b1 &
1!
#5500
0"
#5550
b1 '
1"
#5600
0"
#5650
1"
#5700
0"
#5750
1"
#5800
0"
#5850
1"
#5900
0"
#5950
1"
#6000
0"
#6050
1"
#6100
0"
#6150
1"
#6200
0"
#6250
1"
#6280
b10 &
0!
#6300
0"
#6350
b10 '
1"
#6400
0"
#6450
1"
#6500
0"
#6550
1"
#6600
0"
#6650
1"
#6700
0"
#6750
1"
#6800
0"
#6850
1"
#6900
0"
#6950
1"
#7000
0"
#7050
1"
#7080
1%
b11 &
1!
#7100
0"
#7150
0%
b11 '
1"
#7200
0"
#7250
1"
#7280
1$
b0 &
0!
#7300
0"
#7350
0$
b0 '
1"
#7400
0"
#7450
1"
#7480
b1 &
1!
#7500
0"
#7550
b1 '
1"
#7600
0"
#7650
1"
#7700
0"
#7750
1"
#7800
0"
#7850
1"
#7900
0"
#7950
1"
#8000
0"
#8050
1"
#8100
0"
#8150
1"
#8200
0"
#8250
1"
#8300
0"
#8350
1"
#8400
0"
#8450
1"
#8480
b10 &
0!
#8500
0"
#8550
b10 '
1"
#8600
0"
#8650
1"
#8700
0"
#8750
1"
#8800
0"
#8850
1"
#8880
1%
b11 &
1!
#8900
0"
#8950
0%
b11 '
1"
#9000
0"
#9050
1"
#9100
0"
#9150
1"
#9200
0"
#9250
1"
#9300
0"
#9350
1"
#9400
0"
#9450
1"
#9480
1$
b0 &
0!
#9500
0"
#9550
0$
b0 '
1"
#9600
0"
#9650
1"
#9700
0"
#9750
1"
#9800
0"
#9850
1"
#9900
0"
#9950
1"
#10000
0"
#10050
1"
#10100
0"
#10150
1"
#10200
0"
#10250
1"
#10300
0"
#10350
1"
#10400
0"
#10450
1"
#10480
b1 &
1!
#10500
0"
#10550
b1 '
1"
#10600
0"
#10650
1"
#10680
b10 &
0!
#10700
0"
#10750
b10 '
1"
#10800
0"
#10850
1"
#10900
0"
#10950
1"
#11000
0"
#11050
1"
#11080
1%
b11 &
1!
#11100
0"
#11150
0%
b11 '
1"
#11200
0"
#11250
1"
#11300
0"
#11350
1"
#11400
0"
#11450
1"
#11480
1$
b0 &
0!
#11500
0"
#11550
0$
b0 '
1"
#11600
0"
#11650
1"
#11700
0"
#11750
1"
#11800
0"
#11850
1"
#11900
0"
#11950
1"
#12000
0"
#12050
1"
#12100
0"
#12150
1"
#12200
0"
#12250
1"
#12300
0"
#12350
1"
#12400
0"
#12450
1"
#12480
b1 &
1!
#12500
0"
#12550
b1 '
1"
#12600
0"
#12650
1"
#12700
0"
#12750
1"
#12800
0"
#12850
1"
#12900
0"
#12950
1"
#13000
0"
#13050
1"
#13100
0"
#13150
1"
#13200
0"
#13250
1"
#13300
0"
#13350
1"
#13400
0"
#13450
1"
#13480
b10 &
0!
#13500
0"
#13550
b10 '
1"
#13600
0"
#13650
1"
#13700
0"
#13750
1"
#13800
0"
#13850
1"
#13880
1%
b11 &
1!
#13900
0"
#13950
0%
b11 '
1"
#14000
0"
#14050
1"
#14100
0"
#14150
1"
#14200
0"
#14250
1"
#14300
0"
#14350
1"
#14400
0"
#14450
1"
#14480
1$
b0 &
0!
#14500
0"
#14550
0$
b0 '
1"
#14600
0"
#14650
1"
#14700
0"
#14750
1"
#14800
0"
#14850
1"
#14880
b1 &
1!
#14900
0"
#14950
b1 '
1"
#15000
0"
#15050
1"
#15100
0"
#15150
1"
#15200
0"
#15250
1"
#15280
b10 &
0!
#15300
0"
#15350
b10 '
1"
#15400
0"
#15450
1"
#15480
1%
b11 &
1!
#15500
0"
#15550
0%
b11 '
1"
#15600
0"
#15650
1"
#15700
0"
#15750
1"
#15800
0"
#15850
1"
#15880
1$
b0 &
0!
#15900
0"
#15950
0$
b0 '
1"
#16000
0"
#16050
1"
#16080
b1 &
1!
#16100
0"
#16150
b1 '
1"
#16200
0"
#16250
1"
#16300
0"
#16350
1"
#16400
0"
#16450
1"
#16500
0"
#16550
1"
#16600
0"
#16650
1"
#16680
b10 &
0!
#16700
0"
#16750
b10 '
1"
#16800
0"
#16850
1"
#16880
1%
b11 &
1!
#16900
0"
#16950
0%
b11 '
1"
#17000
0"
#17050
1"
#17100
0"
#17150
1"
#17200
0"
#17250
1"
#17280
1$
b0 &
0!
#17300
0"
#17350
0$
b0 '
1"
#17400
0"
#17450
1"
#17500
0"
#17550
1"
#17600
0"
#17650
1"
#17700
0"
#17750
1"
#17800
0"
#17850
1"
#17900
0"
#17950
1"
#18000
0"
#18050
1"
#18080
b1 &
1!
#18100
0"
#18150
b1 '
1"
#18200
0"
#18250
1"
#18300
0"
#18350
1"
#18400
0"
#18450
1"
#18480
b10 &
0!
#18500
0"
#18550
b10 '
1"
#18600
0"
#18650
1"
#18700
0"
#18750
1"
#18800
0"
#18850
1"
#18880
1%
b11 &
1!
#18900
0"
#18950
0%
b11 '
1"
#19000
0"
#19050
1"
#19100
0"
#19150
1"
#19200
0"
#19250
1"
#19300
0"
#19350
1"
#19400
0"
#19450
1"
#19500
0"
#19550
1"
#19600
0"
#19650
1"
#19700
0"
#19750
1"
#19800
0"
#19850
1"
#19880
1$
b0 &
0!
#19900
0"
#19950
0$
b0 '
1"
#20000
0"
#20050
1"
#20080
b1 &
1!
#20100
0"
#20150
b1 '
1"
#20200
0"
#20250
1"
#20300
0"
#20350
1"
#20400
0"
#20450
1"
#20500
0"
#20550
1"
#20600
0"
#20650
1"
#20680
b10 &
0!
#20700
0"
#20750
b10 '
1"
#20800
0"
#20850
1"
#20900
0"
#20950
1"
#21000
0"
#21050
1"
#21100
0"
#21150
1"
#21200
0"
#21250
1"
#21300
0"
#21350
1"
#21400
0"
#21450
1"
#21500
0"
#21550
1"
#21600
0"
#21650
1"
#21700
0"
#21750
1"
#21800
0"
#21850
1"
#21900
0"
#21950
1"
#22000
0"
#22050
1"
#22080
1%
b11 &
1!
#22100
0"
#22150
0%
b11 '
1"
#22200
0"
#22250
1"
#22300
0"
#22350
1"
#22400
0"
#22450
1"
#22500
0"
#22550
1"
#22600
0"
#22650
1"
#22700
0"
#22750
1"
#22800
0"
#22850
1"
#22900
0"
#22950
1"
#23000
0"
#23050
1"
#23080
1$
b0 &
0!
#23100
0"
#23150
0$
b0 '
1"
#23200
0"
#23250
1"
#23280
b1 &
1!
#23300
0"
#23350
b1 '
1"
#23400
0"
#23450
1"
#23500
0"
#23550
1"
#23600
0"
#23650
1"
#23680
b10 &
0!
#23700
0"
#23750
b10 '
1"
#23800
0"
#23850
1"
#23900
0"
#23950
1"
#24000
0"
#24050
1"
#24080
1%
b11 &
1!
#24100
0"
#24150
0%
b11 '
1"
#24200
0"
#24250
1"
#24300
0"
#24350
1"
#24400
0"
#24450
1"
#24480
1$
b0 &
0!
#24500
0"
#24550
0$
b0 '
1"
#24600
0"
#24650
1"
#24680
b1 &
1!
#24700
0"
#24750
b1 '
1"
#24800
0"
#24850
1"
#24900
0"
#24950
1"
#25000
0"
#25050
1"
#25100
0"
#25150
1"
#25200
0"
#25250
1"
#25300
0"
#25350
1"
#25400
0"
#25450
1"
#25480
b10 &
0!
#25500
0"
#25550
b10 '
1"
#25600
0"
#25650
1"
#25700
0"
#25750
1"
#25800
0"
#25850
1"
#25900
0"
#25950
1"
#26000
0"
#26050
1"
#26080
1%
b11 &
1!
#26100
0"
#26150
0%
b11 '
1"
#26200
0"
#26250
1"
#26280
1$
b0 &
0!
#26300
0"
#26350
0$
b0 '
1"
#26400
0"
#26450
1"
#26500
0"
#26550
1"
#26600
0"
#26650
1"
#26700
0"
#26750
1"
#26800
0"
#26850
1"
#26880
b1 &
1!
#26900
0"
#26950
b1 '
1"
#27000
0"
#27050
1"
#27100
0"
#27150
1"
#27200
0"
#27250
1"
#27280
b10 &
0!
#27300
0"
#27350
b10 '
1"
#27400
0"
#27450
1"
#27500
0"
#27550
1"
#27600
0"
#27650
1"
#27680
1%
b11 &
1!
#27700
0"
#27750
0%
b11 '
1"
#27800
0"
#27850
1"
#27880
1$
b0 &
0!
#27900
0"
#27950
0$
b0 '
1"
#28000
0"
#28050
1"
#28100
0"
#28150
1"
#28200
0"
#28250
1"
#28300
0"
#28350
1"
#28400
0"
#28450
1"
#28480
b1 &
1!
#28500
0"
#28550
b1 '
1"
#28600
0"
#28650
1"
#28680
b10 &
0!
#28700
0"
#28750
b10 '
1"
#28800
0"
#28850
1"
#28900
0"
#28950
1"
#29000
0"
#29050
1"
#29080
1%
b11 &
1!
#29100
0"
#29150
0%
b11 '
1"
#29200
0"
#29250
1"
#29280
1$
b0 &
0!
#29300
0"
#29350
0$
b0 '
1"
#29400
0"
#29450
1"
#29480
b1 &
1!
#29500
0"
#29550
b1 '
1"
#29600
0"
#29650
1"
#29700
0"
#29750
1"
#29800
0"
#29850
1"
#29900
0"
#29950
1"
#30000
0"
#30050
1"
#30100
0"
#30150
1"
#30200
0"
#30250
1"
#30300
0"
#30350
1"
#30400
0"
#30450
1"
#30480
b10 &
0!
#30500
0"
#30550
b10 '
1"
#30600
0"
#30650
1"
#30700
0"
#30750
1"
#30800
0"
#30850
1"
#30900
0"
#30950
1"
#31000
0"
#31050
1"
#31080
1%
b11 &
1!
#31100
0"
#31150
0%
b11 '
1"
#31200
0"
#31250
1"
#31280
1$
b0 &
0!
#31300
0"
#31350
0$
b0 '
1"
#31400
0"
#31450
1"
#31500
0"
#31550
1"
#31600
0"
#31650
1"
#31680
b1 &
1!
#31700
0"
#31750
b1 '
1"
#31800
0"
#31850
1"
#31900
0"
#31950
1"
#32000
0"
#32050
1"
#32080
b10 &
0!
#32100
0"
#32150
b10 '
1"
#32200
0"
#32250
1"
#32300
0"
#32350
1"
#32400
0"
#32450
1"
#32500
0"
#32550
1"
#32600
0"
#32650
1"
#32680
1%
b11 &
1!
#32700
0"
#32750
0%
b11 '
1"
#32800
0"
#32850
1"
#32900
0"
#32950
1"
#33000
0"
#33050
1"
#33080
1$
b0 &
0!
#33100
0"
#33150
0$
b0 '
1"
#33200
0"
#33250
1"
#33300
0"
#33350
1"
#33400
0"
#33450
1"
#33500
0"
#33550
1"
#33600
0"
#33650
1"
#33680
b1 &
1!
#33700
0"
#33750
b1 '
1"
#33800
0"
#33850
1"
#33900
0"
#33950
1"
#34000
0"
#34050
1"
#34080
b10 &
0!
#34100
0"
#34150
b10 '
1"
#34200
0"
#34250
1"
#34300
0"
#34350
1"
#34400
0"
#34450
1"
#34500
0"
#34550
1"
#34600
0"
#34650
1"
#34680
1%
b11 &
1!
#34700
0"
#34750
0%
b11 '
1"
#34800
0"
#34850
1"
#34880
1$
b0 &
0!
#34900
0"
#34950
0$
b0 '
1"
#35000
0"
#35050
1"
#35100
0"
#35150
1"
#35200
0"
#35250
1"
#35280
b1 &
1!
#35300
0"
#35350
b1 '
1"
#35400
0"
#35450
1"
#35480
b10 &
0!
#35500
0"
#35550
b10 '
1"
#35600
0"
#35650
1"
#35700
0"
#35750
1"
#35800
0"
#35850
1"
#35900
0"
#35950
1"
#36000
0"
#36050
1"
#36080
1%
b11 &
1!
#36100
0"
#36150
0%
b11 '
1"
#36200
0"
#36250
1"
#36280
1$
b0 &
0!
#36300
0"
#36350
0$
b0 '
1"
#36400
0"
#36450
1"
#36480
b1 &
1!
#36500
0"
#36550
b1 '
1"
#36600
0"
#36650
1"
#36700
0"
#36750
1"
#36800
0"
#36850
1"
#36880
b10 &
0!
#36900
0"
#36950
b10 '
1"
#37000
0"
#37050
1"
#37100
0"
#37150
1"
#37200
0"
#37250
1"
#37300
0"
#37350
1"
#37400
0"
#37450
1"
#37500
0"
#37550
1"
#37600
0"
#37650
1"
#37680
1%
b11 &
1!
#37700
0"
#37750
0%
b11 '
1"
#37800
0"
#37850
1"
#37880
1$
b0 &
0!
#37900
0"
#37950
0$
b0 '
1"
#38000
0"
#38050
1"
#38100
0"
#38150
1"
#38200
0"
#38250
1"
#38300
0"
#38350
1"
#38400
0"
#38450
1"
#38500
0"
#38550
1"
#38600
0"
#38650
1"
#38680
b1 &
1!
#38700
0"
#38750
b1 '
1"
#38800
0"
#38850
1"
#38900
0"
#38950
1"
#39000
0"
#39050
1"
#39100
0"
#39150
1"
#39200
0"
#39250
1"
#39280
b10 &
0!
#39300
0"
#39350
b10 '
1"
#39400
0"
#39450
1"
#39480
1%
b11 &
1!
#39500
0"
#39550
0%
b11 '
1"
#39600
0"
#39650
1"
#39700
0"
#39750
1"
#39800
0"
#39850
1"
#39900
0"
#39950
1"
#40000
0"
#40050
1"
#40080
1$
b0 &
0!
#40100
0"
#40150
0$
b0 '
1"
#40200
0"
#40250
1"
#40300
0"
#40350
1"
#40400
0"
#40450
1"
#40480
b1 &
1!
#40500
0"
#40550
b1 '
1"
#40600
0"
#40650
1"
#40700
0"
#40750
1"
#40800
0"
#40850
1"
#40900
0"
#40950
1"
#41000
0"
#41050
1"
#41100
0"
#41150
1"
#41200
0"
#41250
1"
#41300
0"
#41350
1"
#41400
0"
#41450
1"
#41480
b10 &
0!
#41500
0"
#41550
b10 '
1"
#41600
0"
#41650
1"
#41680
1%
b11 &
1!
#41700
0"
#41750
0%
b11 '
1"
#41800
0"
#41850
1"
#41900
0"
#41950
1"
#42000
0"
#42050
1"
#42080
1$
b0 &
0!
#42100
0"
#42150
0$
b0 '
1"
#42200
0"
#42250
1"
#42300
0"
#42350
1"
#42400
0"
#42450
1"
#42500
0"
#42550
1"
#42600
0"
#42650
1"
#42700
0"
#42750
1"
#42800
0"
#42850
1"
#42880
b1 &
1!
#42900
0"
#42950
b1 '
1"
#43000
0"
#43050
1"
#43100
0"
#43150
1"
#43200
0"
#43250
1"
#43280
b10 &
0!
#43300
0"
#43350
b10 '
1"
#43400
0"
#43450
1"
#43500
0"
#43550
1"
#43600
0"
#43650
1"
#43680
1%
b11 &
1!
#43700
0"
#43750
0%
b11 '
1"
#43800
0"
#43850
1"
#43880
1$
b0 &
0!
#43900
0"
#43950
0$
b0 '
1"
#44000
0"
#44050
1"
#44100
0"
#44150
1"
#44200
0"
#44250
1"
#44280
b1 &
1!
#44300
0"
#44350
b1 '
1"
#44400
0"
#44450
1"
#44480
b10 &
0!
#44500
0"
#44550
b10 '
1"
#44600
0"
#44650
1"
#44700
0"
#44750
1"
#44800
0"
#44850
1"
#44880
1%
b11 &
1!
#44900
0"
#44950
0%
b11 '
1"
#45000
0"
#45050
1"
#45080
1$
b0 &
0!
#45100
0"
#45150
0$
b0 '
1"
#45200
0"
#45250
1"
#45300
0"
#45350
1"
#45400
0"
#45450
1"
#45480
b1 &
1!
#45500
0"
#45550
b1 '
1"
#45600
0"
#45650
1"
#45700
0"
#45750
1"
#45800
0"
#45850
1"
#45900
0"
#45950
1"
#46000
0"
#46050
1"
#46080
b10 &
0!
#46100
0"
#46150
b10 '
1"
#46200
0"
#46250
1"
#46300
0"
#46350
1"
#46400
0"
#46450
1"
#46500
0"
#46550
1"
#46600
0"
#46650
1"
#46680
1%
b11 &
1!
#46700
0"
#46750
0%
b11 '
1"
#46800
0"
#46850
1"
#46880
1$
b0 &
0!
#46900
0"
#46950
0$
b0 '
1"
#47000
0"
#47050
1"
#47100
0"
#47150
1"
#47200
0"
#47250
1"
#47280
b1 &
1!
#47300
0"
#47350
b1 '
1"
#47400
0"
#47450
1"
#47480
b10 &
0!
#47500
0"
#47550
b10 '
1"
#47600
0"
#47650
1"
#47700
0"
#47750
1"
#47800
0"
#47850
1"
#47900
0"
#47950
1"
#48000
0"
#48050
1"
#48100
0"
#48150
1"
#48200
0"
#48250
1"
#48280
1%
b11 &
1!
#48300
0"
#48350
0%
b11 '
1"
#48400
0"
#48450
1"
#48480
1$
b0 &
0!
#48500
0"
#48550
0$
b0 '
1"
#48600
0"
#48650
1"
#48700
0"
#48750
1"
#48800
0"
#48850
1"
#48900
0"
#48950
1"
#49000
0"
#49050
1"
#49080
b1 &
1!
#49100
0"
#49150
b1 '
1"
#49200
0"
#49250
1"
#49300
0"
#49350
1"
#49400
0"
#49450
1"
#49480
b10 &
0!
#49500
0"
#49550
b10 '
1"
#49600
0"
#49650
1"
#49680
1%
b11 &
1!
#49700
0"
#49750
0%
b11 '
1"
#49800
0"
#49850
1"
#49900
0"
#49950
1"
#50000
0"
#50050
1"
#50100
0"
#50150
1"
#50200
0"
#50250
1"
#50300
0"
#50350
1"
#50400
0"
#50450
1"
#50480
1$
b0 &
0!
#50500
0"
#50550
0$
b0 '
1"
#50600
0"
#50650
1"
#50680
b1 &
1!
#50700
0"
#50750
b1 '
1"
#50800
0"
#50850
1"
#50900
0"
#50950
1"
#51000
0"
#51050
1"
#51100
0"
#51150
1"
#51200
0"
#51250
1"
#51280
b10 &
0!
#51300
0"
#51350
b10 '
1"
#51400
0"
#51450
1"
#51500
0"
#51550
1"
#51600
0"
#51650
1"
#51680
1%
b11 &
1!
#51700
0"
#51750
0%
b11 '
1"
#51800
0"
#51850
1"
#51880
1$
b0 &
0!
#51900
0"
#51950
0$
b0 '
1"
#52000
0"
#52050
1"
#52100
0"
#52150
1"
#52200
0"
#52250
1"
#52280
b1 &
1!
#52300
0"
#52350
b1 '
1"
#52400
0"
#52450
1"
#52500
0"
#52550
1"
#52600
0"
#52650
1"
#52680
b10 &
0!
#52700
0"
#52750
b10 '
1"
#52800
0"
#52850
1"
#52900
0"
#52950
1"
#53000
0"
#53050
1"
#53080
1%
b11 &
1!
#53100
0"
#53150
0%
b11 '
1"
#53200
0"
#53250
1"
#53280
1$
b0 &
0!
#53300
0"
#53350
0$
b0 '
1"
#53400
0"
#53450
1"
#53500
0"
#53550
1"
#53600
0"
#53650
1"
#53680
b1 &
1!
#53700
0"
#53750
b1 '
1"
#53800
0"
#53850
1"
#53880
b10 &
0!
#53900
0"
#53950
b10 '
1"
#54000
0"
#54050
1"
#54080
1%
b11 &
1!
#54100
0"
#54150
0%
b11 '
1"
#54200
0"
#54250
1"
#54300
0"
#54350
1"
#54400
0"
#54450
1"
#54480
1$
b0 &
0!
#54500
0"
#54550
0$
b0 '
1"
#54600
0"
#54650
1"
#54680
b1 &
1!
#54700
0"
#54750
b1 '
1"
#54800
0"
#54850
1"
#54880
b10 &
0!
#54900
0"
#54950
b10 '
1"
#55000
0"
#55050
1"
#55080
1%
b11 &
1!
#55100
0"
#55150
0%
b11 '
1"
#55200
0"
#55250
1"
#55280
1$
b0 &
0!
#55300
0"
#55350
0$
b0 '
1"
#55400
0"
#55450
1"
#55500
0"
#55550
1"
#55600
0"
#55650
1"
#55680
b1 &
1!
#55700
0"
#55750
b1 '
1"
#55800
0"
#55850
1"
#55880
b10 &
0!
#55900
0"
#55950
b10 '
1"
#56000
0"
#56050
1"
#56100
0"
#56150
1"
#56200
0"
#56250
1"
#56300
0"
#56350
1"
#56400
0"
#56450
1"
#56480
1%
b11 &
1!
#56500
0"
#56550
0%
b11 '
1"
#56600
0"
#56650
1"
#56700
0"
#56750
1"
#56800
0"
#56850
1"
#56900
0"
#56950
1"
#57000
0"
#57050
1"
#57100
0"
#57150
1"
#57200
0"
#57250
1"
#57300
0"
#57350
1"
#57400
0"
#57450
1"
#57480
1$
b0 &
0!
#57500
0"
#57550
0$
b0 '
1"
#57600
0"
#57650
1"
#57680
b1 &
1!
#57700
0"
#57750
b1 '
1"
#57800
0"
#57850
1"
#57900
0"
#57950
1"
#58000
0"
#58050
1"
#58100
0"
#58150
1"
#58200
0"
#58250
1"
#58280
b10 &
0!
#58300
0"
#58350
b10 '
1"
#58400
0"
#58450
1"
#58500
0"
#58550
1"
#58600
0"
#58650
1"
#58700
0"
#58750
1"
#58800
0"
#58850
1"
#58900
0"
#58950
1"
#59000
0"
#59050
1"
#59100
0"
#59150
1"
#59200
0"
#59250
1"
#59300
0"
#59350
1"
#59400
0"
#59450
1"
#59480
1%
b11 &
1!
#59500
0"
#59550
0%
b11 '
1"
#59600
0"
#59650
1"
#59700
0"
#59750
1"
#59800
0"
#59850
1"
#59900
0"
#59950
1"
#60000
0"
#60050
1"
#60100
0"
#60150
1"
#60200
0"
#60250
1"
#60300
0"
#60350
1"
#60400
0"
#60450
1"
#60500
0"
#60550
1"
#60600
0"
#60650
1"
#60700
0"
#60750
1"
#60800
0"
#60850
1"
#60880
1$
b0 &
0!
#60900
0"
#60950
0$
b0 '
1"
#61000
0"
#61050
1"
#61080
b1 &
1!
#61100
0"
#61150
b1 '
1"
#61200
0"
#61250
1"
#61300
0"
#61350
1"
#61400
0"
#61450
1"
#61500
0"
#61550
1"
#61600
0"
#61650
1"
#61700
0"
#61750
1"
#61800
0"
#61850
1"
#61900
0"
#61950
1"
#62000
0"
#62050
1"
#62100
0"
#62150
1"
#62200
0"
#62250
1"
#62300
0"
#62350
1"
#62400
0"
#62450
1"
#62500
0"
#62550
1"
#62600
0"
#62650
1"
#62680
b10 &
0!
#62700
0"
#62750
b10 '
1"
#62800
0"
#62850
1"
#62900
0"
#62950
1"
#63000
0"
#63050
1"
#63080
1%
b11 &
1!
#63100
0"
#63150
0%
b11 '
1"
#63200
0"
#63250
1"
#63300
0"
#63350
1"
#63400
0"
#63450
1"
#63480
1$
b0 &
0!
#63500
0"
#63550
0$
b0 '
1"
#63600
0"
#63650
1"
#63700
0"
#63750
1"
#63800
0"
#63850
1"
#63900
0"
#63950
1"
#64000
0"
#64050
1"
#64100
0"
#64150
1"
#64200
0"
#64250
1"
#64280
b1 &
1!
#64300
0"
#64350
b1 '
1"
#64400
0"
#64450
1"
#64480
b10 &
0!
#64500
0"
#64550
b10 '
1"
#64600
0"
#64650
1"
#64700
0"
#64750
1"
#64800
0"
#64850
1"
#64900
0"
#64950
1"
#65000
0"
#65050
1"
#65100
0"
#65150
1"
#65200
0"
#65250
1"
#65300
0"
#65350
1"
#65400
0"
#65450
1"
#65500
0"
#65550
1"
#65600
0"
#65650
1"
#65680
1%
b11 &
1!
#65700
0"
#65750
0%
b11 '
1"
#65800
0"
#65850
1"
#65880
1$
b0 &
0!
#65900
0"
#65950
0$
b0 '
1"
#66000
0"
#66050
1"
#66100
0"
#66150
1"
#66200
0"
#66250
1"
#66280
b1 &
1!
#66300
0"
#66350
b1 '
1"
#66400
0"
#66450
1"
#66480
b10 &
0!
#66500
0"
#66550
b10 '
1"
#66600
0"
#66650
1"
#66700
0"
#66750
1"
#66800
0"
#66850
1"
#66900
0"
#66950
1"
#67000
0"
#67050
1"
#67100
0"
#67150
1"
#67200
0"
#67250
1"
#67280
1%
b11 &
1!
#67300
0"
#67350
0%
b11 '
1"
#67400
0"
#67450
1"
#67500
0"
#67550
1"
#67600
0"
#67650
1"
#67700
0"
#67750
1"
#67800
0"
#67850
1"
#67900
0"
#67950
1"
#68000
0"
#68050
1"
#68100
0"
#68150
1"
#68200
0"
#68250
1"
#68280
1$
b0 &
0!
#68300
0"
#68350
0$
b0 '
1"
#68400
0"
#68450
1"
#68480
b1 &
1!
#68500
0"
#68550
b1 '
1"
#68600
0"
#68650
1"
#68700
0"
#68750
1"
#68800
0"
#68850
1"
#68900
0"
#68950
1"
#69000
0"
#69050
1"
#69080
b10 &
0!
#69100
0"
#69150
b10 '
1"
#69200
0"
#69250
1"
#69280
1%
b11 &
1!
#69300
0"
#69350
0%
b11 '
1"
#69400
0"
#69450
1"
#69480
1$
b0 &
0!
#69500
0"
#69550
0$
b0 '
1"
#69600
0"
#69650
1"
#69700
0"
#69750
1"
#69800
0"
#69850
1"
#69880
b1 &
1!
#69900
0"
#69950
b1 '
1"
#70000
0"
#70050
1"
#70100
0"
#70150
1"
#70200
0"
#70250
1"
#70280
b10 &
0!
#70300
0"
#70350
b10 '
1"
#70400
0"
#70450
1"
#70480
1%
b11 &
1!
#70500
0"
#70550
0%
b11 '
1"
#70600
0"
#70650
1"
#70680
1$
b0 &
0!
#70700
0"
#70750
0$
b0 '
1"
#70800
0"
#70850
1"
#70900
0"
#70950
1"
#71000
0"
#71050
1"
#71080
b1 &
1!
#71100
0"
#71150
b1 '
1"
#71200
0"
#71250
1"
#71280
b10 &
0!
#71300
0"
#71350
b10 '
1"
#71400
0"
#71450
1"
#71500
0"
#71550
1"
#71600
0"
#71650
1"
#71700
0"
#71750
1"
#71800
0"
#71850
1"
#71900
0"
#71950
1"
#72000
0"
#72050
1"
#72080
1%
b11 &
1!
#72100
0"
#72150
0%
b11 '
1"
#72200
0"
#72250
1"
#72300
0"
#72350
1"
#72400
0"
#72450
1"
#72500
0"
#72550
1"
#72600
0"
#72650
1"
#72700
0"
#72750
1"
#72800
0"
#72850
1"
#72880
1$
b0 &
0!
#72900
0"
#72950
0$
b0 '
1"
#73000
0"
#73050
1"
#73080
b1 &
1!
#73100
0"
#73150
b1 '
1"
#73200
0"
#73250
1"
#73300
0"
#73350
1"
#73400
0"
#73450
1"
#73500
0"
#73550
1"
#73600
0"
#73650
1"
#73700
0"
#73750
1"
#73800
0"
#73850
1"
#73900
0"
#73950
1"
#74000
0"
#74050
1"
#74100
0"
#74150
1"
#74200
0"
#74250
1"
#74300
0"
#74350
1"
#74400
0"
#74450
1"
#74480
b10 &
0!
#74500
0"
#74550
b10 '
1"
#74600
0"
#74650
1"
#74680
1%
b11 &
1!
#74700
0"
#74750
0%
b11 '
1"
#74800
0"
#74850
1"
#74880
1$
b0 &
0!
