.history/test.php/时序逻辑/较复杂/seqdet_20210518151059.v
module seqdet (
    x,z,clk,rst
);
input x,clk,rst;
output z;
reg [2:0] state;
wire z;
parameter IDLE = 3'b000;
parameter A =3'001 ;
parameter B =3'b010 ;
parameter C = 3'b011;
parameter D = 3'b100;
parameter E = 3'b101;
parameter F = 3'b110;
parameter G = 3'b111;

always @(posedge clk or negedge rst) begin
    if(!rst)
    state<=IDLE;
    else
    casex (state)
        IDLE:if(x==1)
                state=A;
             else 
                state=IDLE;
        A:if(x==0)
            state=B;
          else if(state==) 
        default: 
    endcase
end

endmodule

test.php/时序逻辑/较复杂/seqdet_tb.v
`include "seqdet.v"
`timescale 1ns/1ns
`define halfperiod 20

module t;
reg clk,rst;
reg [23:0] data;
wire z,x;
assign x=data[23];

initial begin
    clk=0;
    rst=1;
    #2 rst=0;
    #30 rst=1;
    data= 20'b1100_100x_0000_10z1_0100;
    #(`halfperiod*1000)$stop;
end
always #(`halfperiod)clk=~clk;
always @(posedge clk) begin
    #2 data={data[22:0],data[23]};
end
seqdet m(.x(x),.z(z),.clk(clk),.rst(rst));
initial
begin            
    $dumpfile("seqdet.vcd");        //生成的vcd文件名称
    $dumpvars(0, t);     //tb模块名称 0代表这个模块下所有波形 
end
endmodule

test.php/时序逻辑/较复杂/seqdet.vcd
$date
	Tue May 18 15:38:28 2021
$end
$version
	Icarus Verilog
$end
$timescale
	1ns
$end
$scope module t $end
$var wire 1 ! z $end
$var wire 1 " x $end
$var reg 1 # clk $end
$var reg 24 $ data [23:0] $end
$var reg 1 % rst $end
$scope module m $end
$var wire 1 # clk $end
$var wire 1 % rst $end
$var wire 1 " x $end
$var wire 1 ! z $end
$var reg 3 & state [2:0] $end
$upscope $end
$upscope $end
$enddefinitions $end
#0
$dumpvars
bx &
1%
bx $
0#
x"
x!
$end
#2
0!
b0 &
0%
#20
1#
#32
0"
b1100100x000010z10100 $
1%
#40
0#
#60
1#
#62
b1100100x000010z101000 $
#80
0#
#100
1#
#102
b1100100x000010z1010000 $
#120
0#
#140
1#
#142
b1100100x000010z10100000 $
#160
0#
#180
1#
#182
1"
b1100100x000010z101000000 $
#200
0#
#220
b1 &
1#
#222
b100100x000010z1010000001 $
#240
0#
#260
1#
#262
0"
b100x000010z10100000011 $
#280
0#
#300
b10 &
1#
#302
b100x000010z101000000110 $
#320
0#
#340
b11 &
1#
#342
1"
b100x000010z1010000001100 $
#360
0#
#380
b100 &
1#
#382
1!
0"
b0x000010z10100000011001 $
#400
0#
#420
0!
b101 &
1#
#422
b0x000010z101000000110010 $
#440
0#
#460
b11 &
1#
#462
x"
bx000010z1010000001100100 $
#480
0#
#500
b0 &
1#
#502
0"
b10z1010000001100100x $
#520
0#
#540
1#
#542
b10z1010000001100100x0 $
#560
0#
#580
1#
#582
b10z1010000001100100x00 $
#600
0#
#620
1#
#622
b10z1010000001100100x000 $
#640
0#
#660
1#
#662
1"
b10z1010000001100100x0000 $
#680
0#
#700
b1 &
1#
#702
0"
b0z1010000001100100x00001 $
#720
0#
#740
b10 &
1#
#742
z"
bz1010000001100100x000010 $
#760
0#
#780
b0 &
1#
#782
1"
b1010000001100100x000010z $
#800
0#
#820
b1 &
1#
#822
0"
b10000001100100x000010z1 $
#840
0#
#860
b10 &
1#
#862
1"
b10000001100100x000010z10 $
#880
0#
#900
b110 &
1#
#902
0"
b1100100x000010z101 $
#920
0#
#940
b10 &
1#
#942
b1100100x000010z1010 $
#960
0#
#980
b11 &
1#
#982
b1100100x000010z10100 $
#1000
0#
#1020
b111 &
1#
#1022
b1100100x000010z101000 $
#1040
0#
#1060
1#
#1062
b1100100x000010z1010000 $
#1080
0#
#1100
1#
#1102
b1100100x000010z10100000 $
#1120
0#
#1140
1#
#1142
1"
b1100100x000010z101000000 $
#1160
0#
#1180
b110 &
1#
#1182
b100100x000010z1010000001 $
#1200
0#
#1220
b1 &
1#
#1222
0"
b100x000010z10100000011 $
#1240
0#
#1260
b10 &
1#
#1262
b100x000010z101000000110 $
#1280
0#
#1300
b11 &
1#
#1302
1"
b100x000010z1010000001100 $
#1320
0#
#1340
b100 &
1#
#1342
1!
0"
b0x000010z10100000011001 $
#1360
0#
#1380
0!
b101 &
1#
#1382
b0x000010z101000000110010 $
#1400
0#
#1420
b11 &
1#
#1422
x"
bx000010z1010000001100100 $
#1440
0#
#1460
b0 &
1#
#1462
0"
b10z1010000001100100x $
#1480
0#
#1500
1#
#1502
b10z1010000001100100x0 $
#1520
0#
#1540
1#
#1542
b10z1010000001100100x00 $
#1560
0#
#1580
1#
#1582
b10z1010000001100100x000 $
#1600
0#
#1620
1#
#1622
1"
b10z1010000001100100x0000 $
#1640
0#
#1660
b1 &
1#
#1662
0"
b0z1010000001100100x00001 $
#1680
0#
#1700
b10 &
1#
#1702
z"
bz1010000001100100x000010 $
#1720
0#
#1740
b0 &
1#
#1742
1"
b1010000001100100x000010z $
#1760
0#
#1780
b1 &
1#
#1782
0"
b10000001100100x000010z1 $
#1800
0#
#1820
b10 &
1#
#1822
1"
b10000001100100x000010z10 $
#1840
0#
#1860
b110 &
1#
#1862
0"
b1100100x000010z101 $
#1880
0#
#1900
b10 &
1#
#1902
b1100100x000010z1010 $
#1920
0#
#1940
b11 &
1#
#1942
b1100100x000010z10100 $
#1960
0#
#1980
b111 &
1#
#1982
b1100100x000010z101000 $
#2000
0#
#2020
1#
#2022
b1100100x000010z1010000 $
#2040
0#
#2060
1#
#2062
b1100100x000010z10100000 $
#2080
0#
#2100
1#
#2102
1"
b1100100x000010z101000000 $
#2120
0#
#2140
b110 &
1#
#2142
b100100x000010z1010000001 $
#2160
0#
#2180
b1 &
1#
#2182
0"
b100x000010z10100000011 $
#2200
0#
#2220
b10 &
1#
#2222
b100x000010z101000000110 $
#2240
0#
#2260
b11 &
1#
#2262
1"
b100x000010z1010000001100 $
#2280
0#
#2300
b100 &
1#
#2302
1!
0"
b0x000010z10100000011001 $
#2320
0#
#2340
0!
b101 &
1#
#2342
b0x000010z101000000110010 $
#2360
0#
#2380
b11 &
1#
#2382
x"
bx000010z1010000001100100 $
#2400
0#
#2420
b0 &
1#
#2422
0"
b10z1010000001100100x $
#2440
0#
#2460
1#
#2462
b10z1010000001100100x0 $
#2480
0#
#2500
1#
#2502
b10z1010000001100100x00 $
#2520
0#
#2540
1#
#2542
b10z1010000001100100x000 $
#2560
0#
#2580
1#
#2582
1"
b10z1010000001100100x0000 $
#2600
0#
#2620
b1 &
1#
#2622
0"
b0z1010000001100100x00001 $
#2640
0#
#2660
b10 &
1#
#2662
z"
bz1010000001100100x000010 $
#2680
0#
#2700
b0 &
1#
#2702
1"
b1010000001100100x000010z $
#2720
0#
#2740
b1 &
1#
#2742
0"
b10000001100100x000010z1 $
#2760
0#
#2780
b10 &
1#
#2782
1"
b10000001100100x000010z10 $
#2800
0#
#2820
b110 &
1#
#2822
0"
b1100100x000010z101 $
#2840
0#
#2860
b10 &
1#
#2862
b1100100x000010z1010 $
#2880
0#
#2900
b11 &
1#
#2902
b1100100x000010z10100 $
#2920
0#
#2940
b111 &
1#
#2942
b1100100x000010z101000 $
#2960
0#
#2980
1#
#2982
b1100100x000010z1010000 $
#3000
0#
#3020
1#
#3022
b1100100x000010z10100000 $
#3040
0#
#3060
1#
#3062
1"
b1100100x000010z101000000 $
#3080
0#
#3100
b110 &
1#
#3102
b100100x000010z1010000001 $
#3120
0#
#3140
b1 &
1#
#3142
0"
b100x000010z10100000011 $
#3160
0#
#3180
b10 &
1#
#3182
b100x000010z101000000110 $
#3200
0#
#3220
b11 &
1#
#3222
1"
b100x000010z1010000001100 $
#3240
0#
#3260
b100 &
1#
#3262
1!
0"
b0x000010z10100000011001 $
#3280
0#
#3300
0!
b101 &
1#
#3302
b0x000010z101000000110010 $
#3320
0#
#3340
b11 &
1#
#3342
x"
bx000010z1010000001100100 $
#3360
0#
#3380
b0 &
1#
#3382
0"
b10z1010000001100100x $
#3400
0#
#3420
1#
#3422
b10z1010000001100100x0 $
#3440
0#
#3460
1#
#3462
b10z1010000001100100x00 $
#3480
0#
#3500
1#
#3502
b10z1010000001100100x000 $
#3520
0#
#3540
1#
#3542
1"
b10z1010000001100100x0000 $
#3560
0#
#3580
b1 &
1#
#3582
0"
b0z1010000001100100x00001 $
#3600
0#
#3620
b10 &
1#
#3622
z"
bz1010000001100100x000010 $
#3640
0#
#3660
b0 &
1#
#3662
1"
b1010000001100100x000010z $
#3680
0#
#3700
b1 &
1#
#3702
0"
b10000001100100x000010z1 $
#3720
0#
#3740
b10 &
1#
#3742
1"
b10000001100100x000010z10 $
#3760
0#
#3780
b110 &
1#
#3782
0"
b1100100x000010z101 $
#3800
0#
#3820
b10 &
1#
#3822
b1100100x000010z1010 $
#3840
0#
#3860
b11 &
1#
#3862
b1100100x000010z10100 $
#3880
0#
#3900
b111 &
1#
#3902
b1100100x000010z101000 $
#3920
0#
#3940
1#
#3942
b1100100x000010z1010000 $
#3960
0#
#3980
1#
#3982
b1100100x000010z10100000 $
#4000
0#
#4020
1#
#4022
1"
b1100100x000010z101000000 $
#4040
0#
#4060
b110 &
1#
#4062
b100100x000010z1010000001 $
#4080
0#
#4100
b1 &
1#
#4102
0"
b100x000010z10100000011 $
#4120
0#
#4140
b10 &
1#
#4142
b100x000010z101000000110 $
#4160
0#
#4180
b11 &
1#
#4182
1"
b100x000010z1010000001100 $
#4200
0#
#4220
b100 &
1#
#4222
1!
0"
b0x000010z10100000011001 $
#4240
0#
#4260
0!
b101 &
1#
#4262
b0x000010z101000000110010 $
#4280
0#
#4300
b11 &
1#
#4302
x"
bx000010z1010000001100100 $
#4320
0#
#4340
b0 &
1#
#4342
0"
b10z1010000001100100x $
#4360
0#
#4380
1#
#4382
b10z1010000001100100x0 $
#4400
0#
#4420
1#
#4422
b10z1010000001100100x00 $
#4440
0#
#4460
1#
#4462
b10z1010000001100100x000 $
#4480
0#
#4500
1#
#4502
1"
b10z1010000001100100x0000 $
#4520
0#
#4540
b1 &
1#
#4542
0"
b0z1010000001100100x00001 $
#4560
0#
#4580
b10 &
1#
#4582
z"
bz1010000001100100x000010 $
#4600
0#
#4620
b0 &
1#
#4622
1"
b1010000001100100x000010z $
#4640
0#
#4660
b1 &
1#
#4662
0"
b10000001100100x000010z1 $
#4680
0#
#4700
b10 &
1#
#4702
1"
b10000001100100x000010z10 $
#4720
0#
#4740
b110 &
1#
#4742
0"
b1100100x000010z101 $
#4760
0#
#4780
b10 &
1#
#4782
b1100100x000010z1010 $
#4800
0#
#4820
b11 &
1#
#4822
b1100100x000010z10100 $
#4840
0#
#4860
b111 &
1#
#4862
b1100100x000010z101000 $
#4880
0#
#4900
1#
#4902
b1100100x000010z1010000 $
#4920
0#
#4940
1#
#4942
b1100100x000010z10100000 $
#4960
0#
#4980
1#
#4982
1"
b1100100x000010z101000000 $
#5000
0#
#5020
b110 &
1#
#5022
b100100x000010z1010000001 $
#5040
0#
#5060
b1 &
1#
#5062
0"
b100x000010z10100000011 $
#5080
0#
#5100
b10 &
1#
#5102
b100x000010z101000000110 $
#5120
0#
#5140
b11 &
1#
#5142
1"
b100x000010z1010000001100 $
#5160
0#
#5180
b100 &
1#
#5182
1!
0"
b0x000010z10100000011001 $
#5200
0#
#5220
0!
b101 &
1#
#5222
b0x000010z101000000110010 $
#5240
0#
#5260
b11 &
1#
#5262
x"
bx000010z1010000001100100 $
#5280
0#
#5300
b0 &
1#
#5302
0"
b10z1010000001100100x $
#5320
0#
#5340
1#
#5342
b10z1010000001100100x0 $
#5360
0#
#5380
1#
#5382
b10z1010000001100100x00 $
#5400
0#
#5420
1#
#5422
b10z1010000001100100x000 $
#5440
0#
#5460
1#
#5462
1"
b10z1010000001100100x0000 $
#5480
0#
#5500
b1 &
1#
#5502
0"
b0z1010000001100100x00001 $
#5520
0#
#5540
b10 &
1#
#5542
z"
bz1010000001100100x000010 $
#5560
0#
#5580
b0 &
1#
#5582
1"
b1010000001100100x000010z $
#5600
0#
#5620
b1 &
1#
#5622
0"
b10000001100100x000010z1 $
#5640
0#
#5660
b10 &
1#
#5662
1"
b10000001100100x000010z10 $
#5680
0#
#5700
b110 &
1#
#5702
0"
b1100100x000010z101 $
#5720
0#
#5740
b10 &
1#
#5742
b1100100x000010z1010 $
#5760
0#
#5780
b11 &
1#
#5782
b1100100x000010z10100 $
#5800
0#
#5820
b111 &
1#
#5822
b1100100x000010z101000 $
#5840
0#
#5860
1#
#5862
b1100100x000010z1010000 $
#5880
0#
#5900
1#
#5902
b1100100x000010z10100000 $
#5920
0#
#5940
1#
#5942
1"
b1100100x000010z101000000 $
#5960
0#
#5980
b110 &
1#
#5982
b100100x000010z1010000001 $
#6000
0#
#6020
b1 &
1#
#6022
0"
b100x000010z10100000011 $
#6040
0#
#6060
b10 &
1#
#6062
b100x000010z101000000110 $
#6080
0#
#6100
b11 &
1#
#6102
1"
b100x000010z1010000001100 $
#6120
0#
#6140
b100 &
1#
#6142
1!
0"
b0x000010z10100000011001 $
#6160
0#
#6180
0!
b101 &
1#
#6182
b0x000010z101000000110010 $
#6200
0#
#6220
b11 &
1#
#6222
x"
bx000010z1010000001100100 $
#6240
0#
#6260
b0 &
1#
#6262
0"
b10z1010000001100100x $
#6280
0#
#6300
1#
#6302
b10z1010000001100100x0 $
#6320
0#
#6340
1#
#6342
b10z1010000001100100x00 $
#6360
0#
#6380
1#
#6382
b10z1010000001100100x000 $
#6400
0#
#6420
1#
#6422
1"
b10z1010000001100100x0000 $
#6440
0#
#6460
b1 &
1#
#6462
0"
b0z1010000001100100x00001 $
#6480
0#
#6500
b10 &
1#
#6502
z"
bz1010000001100100x000010 $
#6520
0#
#6540
b0 &
1#
#6542
1"
b1010000001100100x000010z $
#6560
0#
#6580
b1 &
1#
#6582
0"
b10000001100100x000010z1 $
#6600
0#
#6620
b10 &
1#
#6622
1"
b10000001100100x000010z10 $
#6640
0#
#6660
b110 &
1#
#6662
0"
b1100100x000010z101 $
#6680
0#
#6700
b10 &
1#
#6702
b1100100x000010z1010 $
#6720
0#
#6740
b11 &
1#
#6742
b1100100x000010z10100 $
#6760
0#
#6780
b111 &
1#
#6782
b1100100x000010z101000 $
#6800
0#
#6820
1#
#6822
b1100100x000010z1010000 $
#6840
0#
#6860
1#
#6862
b1100100x000010z10100000 $
#6880
0#
#6900
1#
#6902
1"
b1100100x000010z101000000 $
#6920
0#
#6940
b110 &
1#
#6942
b100100x000010z1010000001 $
#6960
0#
#6980
b1 &
1#
#6982
0"
b100x000010z10100000011 $
#7000
0#
#7020
b10 &
1#
#7022
b100x000010z101000000110 $
#7040
0#
#7060
b11 &
1#
#7062
1"
b100x000010z1010000001100 $
#7080
0#
#7100
b100 &
1#
#7102
1!
0"
b0x000010z10100000011001 $
#7120
0#
#7140
0!
b101 &
1#
#7142
b0x000010z101000000110010 $
#7160
0#
#7180
b11 &
1#
#7182
x"
bx000010z1010000001100100 $
#7200
0#
#7220
b0 &
1#
#7222
0"
b10z1010000001100100x $
#7240
0#
#7260
1#
#7262
b10z1010000001100100x0 $
#7280
0#
#7300
1#
#7302
b10z1010000001100100x00 $
#7320
0#
#7340
1#
#7342
b10z1010000001100100x000 $
#7360
0#
#7380
1#
#7382
1"
b10z1010000001100100x0000 $
#7400
0#
#7420
b1 &
1#
#7422
0"
b0z1010000001100100x00001 $
#7440
0#
#7460
b10 &
1#
#7462
z"
bz1010000001100100x000010 $
#7480
0#
#7500
b0 &
1#
#7502
1"
b1010000001100100x000010z $
#7520
0#
#7540
b1 &
1#
#7542
0"
b10000001100100x000010z1 $
#7560
0#
#7580
b10 &
1#
#7582
1"
b10000001100100x000010z10 $
#7600
0#
#7620
b110 &
1#
#7622
0"
b1100100x000010z101 $
#7640
0#
#7660
b10 &
1#
#7662
b1100100x000010z1010 $
#7680
0#
#7700
b11 &
1#
#7702
b1100100x000010z10100 $
#7720
0#
#7740
b111 &
1#
#7742
b1100100x000010z101000 $
#7760
0#
#7780
1#
#7782
b1100100x000010z1010000 $
#7800
0#
#7820
1#
#7822
b1100100x000010z10100000 $
#7840
0#
#7860
1#
#7862
1"
b1100100x000010z101000000 $
#7880
0#
#7900
b110 &
1#
#7902
b100100x000010z1010000001 $
#7920
0#
#7940
b1 &
1#
#7942
0"
b100x000010z10100000011 $
#7960
0#
#7980
b10 &
1#
#7982
b100x000010z101000000110 $
#8000
0#
#8020
b11 &
1#
#8022
1"
b100x000010z1010000001100 $
#8040
0#
#8060
b100 &
1#
#8062
1!
0"
b0x000010z10100000011001 $
#8080
0#
#8100
0!
b101 &
1#
#8102
b0x000010z101000000110010 $
#8120
0#
#8140
b11 &
1#
#8142
x"
bx000010z1010000001100100 $
#8160
0#
#8180
b0 &
1#
#8182
0"
b10z1010000001100100x $
#8200
0#
#8220
1#
#8222
b10z1010000001100100x0 $
#8240
0#
#8260
1#
#8262
b10z1010000001100100x00 $
#8280
0#
#8300
1#
#8302
b10z1010000001100100x000 $
#8320
0#
#8340
1#
#8342
1"
b10z1010000001100100x0000 $
#8360
0#
#8380
b1 &
1#
#8382
0"
b0z1010000001100100x00001 $
#8400
0#
#8420
b10 &
1#
#8422
z"
bz1010000001100100x000010 $
#8440
0#
#8460
b0 &
1#
#8462
1"
b1010000001100100x000010z $
#8480
0#
#8500
b1 &
1#
#8502
0"
b10000001100100x000010z1 $
#8520
0#
#8540
b10 &
1#
#8542
1"
b10000001100100x000010z10 $
#8560
0#
#8580
b110 &
1#
#8582
0"
b1100100x000010z101 $
#8600
0#
#8620
b10 &
1#
#8622
b1100100x000010z1010 $
#8640
0#
#8660
b11 &
1#
#8662
b1100100x000010z10100 $
#8680
0#
#8700
b111 &
1#
#8702
b1100100x000010z101000 $
#8720
0#
#8740
1#
#8742
b1100100x000010z1010000 $
#8760
0#
#8780
1#
#8782
b1100100x000010z10100000 $
#8800
0#
#8820
1#
#8822
1"
b1100100x000010z101000000 $
#8840
0#
#8860
b110 &
1#
#8862
b100100x000010z1010000001 $
#8880
0#
#8900
b1 &
1#
#8902
0"
b100x000010z10100000011 $
#8920
0#
#8940
b10 &
1#
#8942
b100x000010z101000000110 $
#8960
0#
#8980
b11 &
1#
#8982
1"
b100x000010z1010000001100 $
#9000
0#
#9020
b100 &
1#
#9022
1!
0"
b0x000010z10100000011001 $
#9040
0#
#9060
0!
b101 &
1#
#9062
b0x000010z101000000110010 $
#9080
0#
#9100
b11 &
1#
#9102
x"
bx000010z1010000001100100 $
#9120
0#
#9140
b0 &
1#
#9142
0"
b10z1010000001100100x $
#9160
0#
#9180
1#
#9182
b10z1010000001100100x0 $
#9200
0#
#9220
1#
#9222
b10z1010000001100100x00 $
#9240
0#
#9260
1#
#9262
b10z1010000001100100x000 $
#9280
0#
#9300
1#
#9302
1"
b10z1010000001100100x0000 $
#9320
0#
#9340
b1 &
1#
#9342
0"
b0z1010000001100100x00001 $
#9360
0#
#9380
b10 &
1#
#9382
z"
bz1010000001100100x000010 $
#9400
0#
#9420
b0 &
1#
#9422
1"
b1010000001100100x000010z $
#9440
0#
#9460
b1 &
1#
#9462
0"
b10000001100100x000010z1 $
#9480
0#
#9500
b10 &
1#
#9502
1"
b10000001100100x000010z10 $
#9520
0#
#9540
b110 &
1#
#9542
0"
b1100100x000010z101 $
#9560
0#
#9580
b10 &
1#
#9582
b1100100x000010z1010 $
#9600
0#
#9620
b11 &
1#
#9622
b1100100x000010z10100 $
#9640
0#
#9660
b111 &
1#
#9662
b1100100x000010z101000 $
#9680
0#
#9700
1#
#9702
b1100100x000010z1010000 $
#9720
0#
#9740
1#
#9742
b1100100x000010z10100000 $
#9760
0#
#9780
1#
#9782
1"
b1100100x000010z101000000 $
#9800
0#
#9820
b110 &
1#
#9822
b100100x000010z1010000001 $
#9840
0#
#9860
b1 &
1#
#9862
0"
b100x000010z10100000011 $
#9880
0#
#9900
b10 &
1#
#9902
b100x000010z101000000110 $
#9920
0#
#9940
b11 &
1#
#9942
1"
b100x000010z1010000001100 $
#9960
0#
#9980
b100 &
1#
#9982
1!
0"
b0x000010z10100000011001 $
#10000
0#
#10020
0!
b101 &
1#
#10022
b0x000010z101000000110010 $
#10040
0#
#10060
b11 &
1#
#10062
x"
bx000010z1010000001100100 $
#10080
0#
#10100
b0 &
1#
#10102
0"
b10z1010000001100100x $
#10120
0#
#10140
1#
#10142
b10z1010000001100100x0 $
#10160
0#
#10180
1#
#10182
b10z1010000001100100x00 $
#10200
0#
#10220
1#
#10222
b10z1010000001100100x000 $
#10240
0#
#10260
1#
#10262
1"
b10z1010000001100100x0000 $
#10280
0#
#10300
b1 &
1#
#10302
0"
b0z1010000001100100x00001 $
#10320
0#
#10340
b10 &
1#
#10342
z"
bz1010000001100100x000010 $
#10360
0#
#10380
b0 &
1#
#10382
1"
b1010000001100100x000010z $
#10400
0#
#10420
b1 &
1#
#10422
0"
b10000001100100x000010z1 $
#10440
0#
#10460
b10 &
1#
#10462
1"
b10000001100100x000010z10 $
#10480
0#
#10500
b110 &
1#
#10502
0"
b1100100x000010z101 $
#10520
0#
#10540
b10 &
1#
#10542
b1100100x000010z1010 $
#10560
0#
#10580
b11 &
1#
#10582
b1100100x000010z10100 $
#10600
0#
#10620
b111 &
1#
#10622
b1100100x000010z101000 $
#10640
0#
#10660
1#
#10662
b1100100x000010z1010000 $
#10680
0#
#10700
1#
#10702
b1100100x000010z10100000 $
#10720
0#
#10740
1#
#10742
1"
b1100100x000010z101000000 $
#10760
0#
#10780
b110 &
1#
#10782
b100100x000010z1010000001 $
#10800
0#
#10820
b1 &
1#
#10822
0"
b100x000010z10100000011 $
#10840
0#
#10860
b10 &
1#
#10862
b100x000010z101000000110 $
#10880
0#
#10900
b11 &
1#
#10902
1"
b100x000010z1010000001100 $
#10920
0#
#10940
b100 &
1#
#10942
1!
0"
b0x000010z10100000011001 $
#10960
0#
#10980
0!
b101 &
1#
#10982
b0x000010z101000000110010 $
#11000
0#
#11020
b11 &
1#
#11022
x"
bx000010z1010000001100100 $
#11040
0#
#11060
b0 &
1#
#11062
0"
b10z1010000001100100x $
#11080
0#
#11100
1#
#11102
b10z1010000001100100x0 $
#11120
0#
#11140
1#
#11142
b10z1010000001100100x00 $
#11160
0#
#11180
1#
#11182
b10z1010000001100100x000 $
#11200
0#
#11220
1#
#11222
1"
b10z1010000001100100x0000 $
#11240
0#
#11260
b1 &
1#
#11262
0"
b0z1010000001100100x00001 $
#11280
0#
#11300
b10 &
1#
#11302
z"
bz1010000001100100x000010 $
#11320
0#
#11340
b0 &
1#
#11342
1"
b1010000001100100x000010z $
#11360
0#
#11380
b1 &
1#
#11382
0"
b10000001100100x000010z1 $
#11400
0#
#11420
b10 &
1#
#11422
1"
b10000001100100x000010z10 $
#11440
0#
#11460
b110 &
1#
#11462
0"
b1100100x000010z101 $
#11480
0#
#11500
b10 &
1#
#11502
b1100100x000010z1010 $
#11520
0#
#11540
b11 &
1#
#11542
b1100100x000010z10100 $
#11560
0#
#11580
b111 &
1#
#11582
b1100100x000010z101000 $
#11600
0#
#11620
1#
#11622
b1100100x000010z1010000 $
#11640
0#
#11660
1#
#11662
b1100100x000010z10100000 $
#11680
0#
#11700
1#
#11702
1"
b1100100x000010z101000000 $
#11720
0#
#11740
b110 &
1#
#11742
b100100x000010z1010000001 $
#11760
0#
#11780
b1 &
1#
#11782
0"
b100x000010z10100000011 $
#11800
0#
#11820
b10 &
1#
#11822
b100x000010z101000000110 $
#11840
0#
#11860
b11 &
1#
#11862
1"
b100x000010z1010000001100 $
#11880
0#
#11900
b100 &
1#
#11902
1!
0"
b0x000010z10100000011001 $
#11920
0#
#11940
0!
b101 &
1#
#11942
b0x000010z101000000110010 $
#11960
0#
#11980
b11 &
1#
#11982
x"
bx000010z1010000001100100 $
#12000
0#
#12020
b0 &
1#
#12022
0"
b10z1010000001100100x $
#12040
0#
#12060
1#
#12062
b10z1010000001100100x0 $
#12080
0#
#12100
1#
#12102
b10z1010000001100100x00 $
#12120
0#
#12140
1#
#12142
b10z1010000001100100x000 $
#12160
0#
#12180
1#
#12182
1"
b10z1010000001100100x0000 $
#12200
0#
#12220
b1 &
1#
#12222
0"
b0z1010000001100100x00001 $
#12240
0#
#12260
b10 &
1#
#12262
z"
bz1010000001100100x000010 $
#12280
0#
#12300
b0 &
1#
#12302
1"
b1010000001100100x000010z $
#12320
0#
#12340
b1 &
1#
#12342
0"
b10000001100100x000010z1 $
#12360
0#
#12380
b10 &
1#
#12382
1"
b10000001100100x000010z10 $
#12400
0#
#12420
b110 &
1#
#12422
0"
b1100100x000010z101 $
#12440
0#
#12460
b10 &
1#
#12462
b1100100x000010z1010 $
#12480
0#
#12500
b11 &
1#
#12502
b1100100x000010z10100 $
#12520
0#
#12540
b111 &
1#
#12542
b1100100x000010z101000 $
#12560
0#
#12580
1#
#12582
b1100100x000010z1010000 $
#12600
0#
#12620
1#
#12622
b1100100x000010z10100000 $
#12640
0#
#12660
1#
#12662
1"
b1100100x000010z101000000 $
#12680
0#
#12700
b110 &
1#
#12702
b100100x000010z1010000001 $
#12720
0#
#12740
b1 &
1#
#12742
0"
b100x000010z10100000011 $
#12760
0#
#12780
b10 &
1#
#12782
b100x000010z101000000110 $
#12800
0#
#12820
b11 &
1#
#12822
1"
b100x000010z1010000001100 $
#12840
0#
#12860
b100 &
1#
#12862
1!
0"
b0x000010z10100000011001 $
#12880
0#
#12900
0!
b101 &
1#
#12902
b0x000010z101000000110010 $
#12920
0#
#12940
b11 &
1#
#12942
x"
bx000010z1010000001100100 $
#12960
0#
#12980
b0 &
1#
#12982
0"
b10z1010000001100100x $
#13000
0#
#13020
1#
#13022
b10z1010000001100100x0 $
#13040
0#
#13060
1#
#13062
b10z1010000001100100x00 $
#13080
0#
#13100
1#
#13102
b10z1010000001100100x000 $
#13120
0#
#13140
1#
#13142
1"
b10z1010000001100100x0000 $
#13160
0#
#13180
b1 &
1#
#13182
0"
b0z1010000001100100x00001 $
#13200
0#
#13220
b10 &
1#
#13222
z"
bz1010000001100100x000010 $
#13240
0#
#13260
b0 &
1#
#13262
1"
b1010000001100100x000010z $
#13280
0#
#13300
b1 &
1#
#13302
0"
b10000001100100x000010z1 $
#13320
0#
#13340
b10 &
1#
#13342
1"
b10000001100100x000010z10 $
#13360
0#
#13380
b110 &
1#
#13382
0"
b1100100x000010z101 $
#13400
0#
#13420
b10 &
1#
#13422
b1100100x000010z1010 $
#13440
0#
#13460
b11 &
1#
#13462
b1100100x000010z10100 $
#13480
0#
#13500
b111 &
1#
#13502
b1100100x000010z101000 $
#13520
0#
#13540
1#
#13542
b1100100x000010z1010000 $
#13560
0#
#13580
1#
#13582
b1100100x000010z10100000 $
#13600
0#
#13620
1#
#13622
1"
b1100100x000010z101000000 $
#13640
0#
#13660
b110 &
1#
#13662
b100100x000010z1010000001 $
#13680
0#
#13700
b1 &
1#
#13702
0"
b100x000010z10100000011 $
#13720
0#
#13740
b10 &
1#
#13742
b100x000010z101000000110 $
#13760
0#
#13780
b11 &
1#
#13782
1"
b100x000010z1010000001100 $
#13800
0#
#13820
b100 &
1#
#13822
1!
0"
b0x000010z10100000011001 $
#13840
0#
#13860
0!
b101 &
1#
#13862
b0x000010z101000000110010 $
#13880
0#
#13900
b11 &
1#
#13902
x"
bx000010z1010000001100100 $
#13920
0#
#13940
b0 &
1#
#13942
0"
b10z1010000001100100x $
#13960
0#
#13980
1#
#13982
b10z1010000001100100x0 $
#14000
0#
#14020
1#
#14022
b10z1010000001100100x00 $
#14040
0#
#14060
1#
#14062
b10z1010000001100100x000 $
#14080
0#
#14100
1#
#14102
1"
b10z1010000001100100x0000 $
#14120
0#
#14140
b1 &
1#
#14142
0"
b0z1010000001100100x00001 $
#14160
0#
#14180
b10 &
1#
#14182
z"
bz1010000001100100x000010 $
#14200
0#
#14220
b0 &
1#
#14222
1"
b1010000001100100x000010z $
#14240
0#
#14260
b1 &
1#
#14262
0"
b10000001100100x000010z1 $
#14280
0#
#14300
b10 &
1#
#14302
1"
b10000001100100x000010z10 $
#14320
0#
#14340
b110 &
1#
#14342
0"
b1100100x000010z101 $
#14360
0#
#14380
b10 &
1#
#14382
b1100100x000010z1010 $
#14400
0#
#14420
b11 &
1#
#14422
b1100100x000010z10100 $
#14440
0#
#14460
b111 &
1#
#14462
b1100100x000010z101000 $
#14480
0#
#14500
1#
#14502
b1100100x000010z1010000 $
#14520
0#
#14540
1#
#14542
b1100100x000010z10100000 $
#14560
0#
#14580
1#
#14582
1"
b1100100x000010z101000000 $
#14600
0#
#14620
b110 &
1#
#14622
b100100x000010z1010000001 $
#14640
0#
#14660
b1 &
1#
#14662
0"
b100x000010z10100000011 $
#14680
0#
#14700
b10 &
1#
#14702
b100x000010z101000000110 $
#14720
0#
#14740
b11 &
1#
#14742
1"
b100x000010z1010000001100 $
#14760
0#
#14780
b100 &
1#
#14782
1!
0"
b0x000010z10100000011001 $
#14800
0#
#14820
0!
b101 &
1#
#14822
b0x000010z101000000110010 $
#14840
0#
#14860
b11 &
1#
#14862
x"
bx000010z1010000001100100 $
#14880
0#
#14900
b0 &
1#
#14902
0"
b10z1010000001100100x $
#14920
0#
#14940
1#
#14942
b10z1010000001100100x0 $
#14960
0#
#14980
1#
#14982
b10z1010000001100100x00 $
#15000
0#
#15020
1#
#15022
b10z1010000001100100x000 $
#15040
0#
#15060
1#
#15062
1"
b10z1010000001100100x0000 $
#15080
0#
#15100
b1 &
1#
#15102
0"
b0z1010000001100100x00001 $
#15120
0#
#15140
b10 &
1#
#15142
z"
bz1010000001100100x000010 $
#15160
0#
#15180
b0 &
1#
#15182
1"
b1010000001100100x000010z $
#15200
0#
#15220
b1 &
1#
#15222
0"
b10000001100100x000010z1 $
#15240
0#
#15260
b10 &
1#
