.history/test.php/时序逻辑/并行数据/out16hi_20210518170114.v
module out16hi(scl,sda,outhigh);
input scl,sda;
output [15:0] outhigh;
reg [5:0] mstate;
reg [3:0] pdata,
            padatabuf;
reg [15:0] outhigh;
reg StartFlag,EndFlag;
always @(negedge sda) begin
    if(scl)
    begin
      StartFlag<=1;
    end
    else if(EndFlag)
        
end
endmodule

.history/test.php/时序逻辑/并行数据/ptosda_20210518161830.v
module ptosda(rst,sclk,ack,scl,sda,data);
input sclk,rst;
input [3:0] data;
output ack,scl,sda;
reg scl,link_sda,ack,sdabuf;
reg [3:0] databuf;
reg [7:0] state;
parameter  = ;

endmodule

.history/test.php/时序逻辑/并行数据/sigdata_20210518172555.v
`timescale 1ns/1ns
`define halfperiod 50
module sigdata(rst,sclk,data,ask_for_data);
output rst;
output [3:0] data;
output sclk;
input ask_for_data;
reg rst,sclk;

initial begin
    rst=1;
    #1
end
endmodule

.history/test.php/时序逻辑/并行数据/top_20210518173253.v
`timescale 1ns/1ns
`include "sigdata.v"
`include "ptosda.v"
`include "out16hi.v"

module top();
wire [3:0] data;
wire sclk;
wire scl;
wire sda;
wire rst;
wire [15:0] outhigh;
sigdata m0(.rst(rst),.sclk(sclk),.data(data),.ask_for_data(ack));
ptosda m1(.rst(rst),.sclk(sclk),.ack(ack),.scl(scl),.sda(sda),.data(data));
out16hi m2(.scl(scl),.sda(sda),.outhigh(outhigh));
initial
begin            
    $dumpfile("seqdet.vcd");        //生成的vcd文件名称
    $dumpvars(0, t);     //tb模块名称 0代表这个模块下所有波形 
end
endmodule

test.php/时序逻辑/并行数据/top.vcd
$date
	Tue May 18 18:52:19 2021
$end
$version
	Icarus Verilog
$end
$timescale
	1ns
$end
$scope module top $end
$var wire 1 ! sda $end
$var wire 1 " sclk $end
$var wire 1 # scl $end
$var wire 1 $ rst $end
$var wire 16 % outhigh [15:0] $end
$var wire 4 & data [3:0] $end
$var wire 1 ' ack $end
$scope module m0 $end
$var wire 1 ' ask_for_data $end
$var reg 4 ( data [3:0] $end
$var reg 1 $ rst $end
$var reg 1 " sclk $end
$upscope $end
$scope module m1 $end
$var wire 4 ) data [3:0] $end
$var wire 1 $ rst $end
$var wire 1 " sclk $end
$var wire 1 ! sda $end
$var reg 1 ' ack $end
$var reg 4 * databuf [3:0] $end
$var reg 1 + link_sda $end
$var reg 1 # scl $end
$var reg 1 , sdabuf $end
$var reg 8 - state [7:0] $end
$upscope $end
$scope module m2 $end
$var wire 1 # scl $end
$var wire 1 ! sda $end
$var reg 1 . EndFlag $end
$var reg 1 / StartFlag $end
$var reg 6 0 mstate [5:0] $end
$var reg 16 1 outhigh [15:0] $end
$var reg 4 2 padatabuf [3:0] $end
$var reg 4 3 pdata [3:0] $end
$upscope $end
$upscope $end
$enddefinitions $end
#0
$dumpvars
bx 3
bx 2
bx 1
bx 0
x/
x.
bx -
x,
x+
bx *
b0 )
b0 (
x'
b0 &
bx %
1$
x#
0"
x!
$end
#10
1/
b1 0
0!
0'
1,
b0 -
0+
1#
0$
#50
1"
#100
0"
#113
1$
#150
0#
1"
#200
b0 *
1'
0"
#228
b1 &
b1 (
b1 )
#250
b0xxx 3
b10 0
1#
1"
#300
b0xxx 2
1.
1!
b1 -
1+
0"
#350
0#
1"
#400
0"
#450
b1xx 3
b100 0
1#
1"
#500
0!
b10 -
0,
0"
#550
0#
1"
#600
0'
b100 -
0"
#650
b10x 3
b1000 0
1#
1"
#700
0"
#750
0#
1"
#800
b1000 -
0"
#850
b100 3
b10000 0
1#
1"
#900
0"
#950
0#
1"
#1000
b10000 -
0"
#1050
b1 0
1#
1"
#1100
0"
#1150
0#
1"
#1200
b100000 -
0"
#1250
b10 0
1#
1"
#1300
0"
#1350
0#
1"
#1400
b1000000 -
0"
#1450
b0 3
b100 0
1#
1"
#1500
b1000000000000000 %
b1000000000000000 1
b0 2
1!
b10000000 -
1,
0"
#1550
0#
1"
#1600
0/
0!
b0 -
0+
0"
#1650
b1 0
1#
1"
#1700
b1 *
1'
0"
#1728
b10 &
b10 (
b10 )
#1750
0#
1"
#1800
0.
1!
b1 -
1+
0"
#1850
1#
1"
#1900
1/
0!
b10 -
0,
0"
#1950
0#
1"
#2000
0'
b100 -
0"
#2050
b10 0
1#
1"
#2100
0"
#2150
0#
1"
#2200
b1000 -
0"
#2250
b100 0
1#
1"
#2300
0"
#2350
0#
1"
#2400
b10000 -
0"
#2450
b1000 0
1#
1"
#2500
0"
#2550
0#
1"
#2600
1!
b100000 -
1,
0"
#2650
b1 3
b10000 0
1#
1"
#2700
0"
#2750
0#
1"
#2800
0!
b1000000 -
0,
0"
#2850
b1 0
1#
1"
#2900
b1 %
b1 1
b1 2
1.
1!
b10000000 -
1,
0"
#2950
0#
1"
#3000
0/
0!
b0 -
0+
0"
#3050
1#
1"
#3100
b10 *
1'
0"
#3128
b11 &
b11 (
b11 )
#3150
0#
1"
#3200
0.
1!
b1 -
1+
0"
#3250
1#
1"
#3300
1/
0!
b10 -
0,
0"
#3350
0#
1"
#3400
0'
b100 -
0"
#3450
b10 0
1#
1"
#3500
0"
#3550
0#
1"
#3600
b1000 -
0"
#3650
b100 0
1#
1"
#3700
0"
#3750
0#
1"
#3800
1!
b10000 -
1,
0"
#3850
b11 3
b1000 0
1#
1"
#3900
0"
#3950
0#
1"
#4000
0!
b100000 -
0,
0"
#4050
b10 3
b10000 0
1#
1"
#4100
0"
#4150
0#
1"
#4200
b1000000 -
0"
#4250
b1 0
1#
1"
#4300
b10 %
b10 1
b10 2
1.
1!
b10000000 -
1,
0"
#4350
0#
1"
#4400
0/
0!
b0 -
0+
0"
#4450
1#
1"
#4500
b11 *
1'
0"
#4528
b100 &
b100 (
b100 )
#4550
0#
1"
#4600
0.
1!
b1 -
1+
0"
#4650
1#
1"
#4700
1/
0!
b10 -
0,
0"
#4750
0#
1"
#4800
0'
b100 -
0"
#4850
b10 0
1#
1"
#4900
0"
#4950
0#
1"
#5000
b1000 -
0"
#5050
b100 0
1#
1"
#5100
0"
#5150
0#
1"
#5200
1!
b10000 -
1,
0"
#5250
b1000 0
1#
1"
#5300
0"
#5350
0#
1"
#5400
b100000 -
0"
#5450
b11 3
b10000 0
1#
1"
#5500
0"
#5550
0#
1"
#5600
0!
b1000000 -
0,
0"
#5650
b1 0
1#
1"
#5700
b100 %
b100 1
b11 2
1.
1!
b10000000 -
1,
0"
#5750
0#
1"
#5800
0/
0!
b0 -
0+
0"
#5850
1#
1"
#5900
b100 *
1'
0"
#5928
b101 &
b101 (
b101 )
#5950
0#
1"
#6000
0.
1!
b1 -
1+
0"
#6050
1#
1"
#6100
1/
0!
b10 -
0,
0"
#6150
0#
1"
#6200
0'
b100 -
0"
#6250
b10 0
1#
1"
#6300
0"
#6350
0#
1"
#6400
1!
b1000 -
1,
0"
#6450
b111 3
b100 0
1#
1"
#6500
0"
#6550
0#
1"
#6600
0!
b10000 -
0,
0"
#6650
b101 3
b1000 0
1#
1"
#6700
0"
#6750
0#
1"
#6800
b100000 -
0"
#6850
b100 3
b10000 0
1#
1"
#6900
0"
#6950
0#
1"
#7000
b1000000 -
0"
#7050
b1 0
1#
1"
#7100
b1000 %
b1000 1
b100 2
1.
1!
b10000000 -
1,
0"
#7150
0#
1"
#7200
0/
0!
b0 -
0+
0"
#7250
1#
1"
#7300
b101 *
1'
0"
#7328
b110 &
b110 (
b110 )
#7350
0#
1"
#7400
0.
1!
b1 -
1+
0"
#7450
1#
1"
#7500
1/
0!
b10 -
0,
0"
#7550
0#
1"
#7600
0'
b100 -
0"
#7650
b10 0
1#
1"
#7700
0"
#7750
0#
1"
#7800
1!
b1000 -
1,
0"
#7850
b100 0
1#
1"
#7900
0"
#7950
0#
1"
#8000
0!
b10000 -
0,
0"
#8050
b1000 0
1#
1"
#8100
0"
#8150
0#
1"
#8200
1!
b100000 -
1,
0"
#8250
b101 3
b10000 0
1#
1"
#8300
0"
#8350
0#
1"
#8400
0!
b1000000 -
0,
0"
#8450
b1 0
1#
1"
#8500
b10000 %
b10000 1
b101 2
1.
1!
b10000000 -
1,
0"
#8550
0#
1"
#8600
0/
0!
b0 -
0+
0"
#8650
1#
1"
#8700
b110 *
1'
0"
#8728
b111 &
b111 (
b111 )
#8750
0#
1"
#8800
0.
1!
b1 -
1+
0"
#8850
1#
1"
#8900
1/
0!
b10 -
0,
0"
#8950
0#
1"
#9000
0'
b100 -
0"
#9050
b10 0
1#
1"
#9100
0"
#9150
0#
1"
#9200
1!
b1000 -
1,
0"
#9250
b100 0
1#
1"
#9300
0"
#9350
0#
1"
#9400
b10000 -
0"
#9450
b111 3
b1000 0
1#
1"
#9500
0"
#9550
0#
1"
#9600
0!
b100000 -
0,
0"
#9650
b110 3
b10000 0
1#
1"
#9700
0"
#9750
0#
1"
#9800
b1000000 -
0"
#9850
b1 0
1#
1"
#9900
b100000 %
b100000 1
b110 2
1.
1!
b10000000 -
1,
0"
#9950
0#
1"
#10000
0/
0!
b0 -
0+
0"
#10050
1#
1"
#10100
b111 *
1'
0"
#10128
b1000 &
b1000 (
b1000 )
#10150
0#
1"
#10200
0.
1!
b1 -
1+
0"
#10250
1#
1"
#10300
1/
0!
b10 -
0,
0"
#10350
0#
1"
#10400
0'
b100 -
0"
#10450
b10 0
1#
1"
#10500
0"
#10550
0#
1"
#10600
1!
b1000 -
1,
0"
#10650
b100 0
1#
1"
#10700
0"
#10750
0#
1"
#10800
b10000 -
0"
#10850
b1000 0
1#
1"
#10900
0"
#10950
0#
1"
#11000
b100000 -
0"
#11050
b111 3
b10000 0
1#
1"
#11100
0"
#11150
0#
1"
#11200
0!
b1000000 -
0,
0"
#11250
b1 0
1#
1"
#11300
b1000000 %
b1000000 1
b111 2
1.
1!
b10000000 -
1,
0"
#11350
0#
1"
#11400
0/
0!
b0 -
0+
0"
#11450
1#
1"
#11500
b1000 *
1'
0"
#11528
b1001 &
b1001 (
b1001 )
#11550
0#
1"
#11600
0.
1!
b1 -
1+
0"
#11650
1#
1"
#11700
1/
0!
b10 -
0,
0"
#11750
0#
1"
#11800
1!
0'
b100 -
1,
0"
#11850
b1111 3
b10 0
1#
1"
#11900
0"
#11950
0#
1"
#12000
0!
b1000 -
0,
0"
#12050
b1011 3
b100 0
1#
1"
#12100
0"
#12150
0#
1"
#12200
b10000 -
0"
#12250
b1001 3
b1000 0
1#
1"
#12300
0"
#12350
0#
1"
#12400
b100000 -
0"
#12450
b1000 3
b10000 0
1#
1"
#12500
0"
#12550
0#
1"
#12600
b1000000 -
0"
#12650
b1 0
1#
1"
#12700
b10000000 %
b10000000 1
b1000 2
1.
1!
b10000000 -
1,
0"
#12750
0#
1"
#12800
0/
0!
b0 -
0+
0"
#12850
1#
1"
#12900
b1001 *
1'
0"
#12928
b1010 &
b1010 (
b1010 )
#12950
0#
1"
#13000
0.
1!
b1 -
1+
0"
#13050
1#
1"
#13100
1/
0!
b10 -
0,
0"
#13150
0#
1"
#13200
1!
0'
b100 -
1,
0"
#13250
b10 0
1#
1"
#13300
0"
#13350
0#
1"
#13400
0!
b1000 -
0,
0"
#13450
b100 0
1#
1"
#13500
0"
#13550
0#
1"
#13600
b10000 -
0"
#13650
b1000 0
1#
1"
#13700
0"
#13750
0#
1"
#13800
1!
b100000 -
1,
0"
#13850
b1001 3
b10000 0
1#
1"
#13900
0"
#13950
0#
1"
#14000
0!
b1000000 -
0,
0"
#14050
b1 0
1#
1"
#14100
b100000000 %
b100000000 1
b1001 2
1.
1!
b10000000 -
1,
0"
#14150
0#
1"
#14200
0/
0!
b0 -
0+
0"
#14250
1#
1"
#14300
b1010 *
1'
0"
#14328
b1011 &
b1011 (
b1011 )
#14350
0#
1"
#14400
0.
1!
b1 -
1+
0"
#14450
1#
1"
#14500
1/
0!
b10 -
0,
0"
#14550
0#
1"
#14600
1!
0'
b100 -
1,
0"
#14650
b10 0
1#
1"
#14700
0"
#14750
0#
1"
#14800
0!
b1000 -
0,
0"
#14850
b100 0
1#
1"
#14900
0"
#14950
0#
1"
#15000
1!
b10000 -
1,
0"
#15050
b1011 3
b1000 0
1#
1"
#15100
0"
#15150
0#
1"
#15200
0!
b100000 -
0,
0"
#15250
b1010 3
b10000 0
1#
1"
#15300
0"
#15350
0#
1"
#15400
b1000000 -
0"
#15450
b1 0
1#
1"
#15500
b1000000000 %
b1000000000 1
b1010 2
1.
1!
b10000000 -
1,
0"
#15550
0#
1"
#15600
0/
0!
b0 -
0+
0"
#15650
1#
1"
#15700
b1011 *
1'
0"
#15728
b1100 &
b1100 (
b1100 )
#15750
0#
1"
#15800
0.
1!
b1 -
1+
0"
#15850
1#
1"
#15900
1/
0!
b10 -
0,
0"
#15950
0#
1"
#16000
1!
0'
b100 -
1,
0"
#16050
b10 0
1#
1"
#16100
0"
#16150
0#
1"
#16200
0!
b1000 -
0,
0"
#16250
b100 0
1#
1"
#16300
0"
#16350
0#
1"
#16400
1!
b10000 -
1,
0"
#16450
b1000 0
1#
1"
#16500
0"
#16550
0#
1"
#16600
b100000 -
0"
#16650
b1011 3
b10000 0
1#
1"
#16700
0"
#16750
0#
1"
#16800
0!
b1000000 -
0,
0"
#16850
b1 0
1#
1"
#16900
b10000000000 %
b10000000000 1
b1011 2
1.
1!
b10000000 -
1,
0"
#16950
0#
1"
#17000
0/
0!
b0 -
0+
0"
#17050
1#
1"
#17100
b1100 *
1'
0"
#17128
b1101 &
b1101 (
b1101 )
#17150
0#
1"
#17200
0.
1!
b1 -
1+
0"
#17250
1#
1"
#17300
1/
0!
b10 -
0,
0"
#17350
0#
1"
#17400
1!
0'
b100 -
1,
0"
#17450
b10 0
1#
1"
#17500
0"
#17550
0#
1"
#17600
b1000 -
0"
#17650
b1111 3
b100 0
1#
1"
#17700
0"
#17750
0#
1"
#17800
0!
b10000 -
0,
0"
#17850
b1101 3
b1000 0
1#
1"
#17900
0"
#17950
0#
1"
#18000
b100000 -
0"
#18050
b1100 3
b10000 0
1#
1"
#18100
0"
#18150
0#
1"
#18200
b1000000 -
0"
#18250
b1 0
1#
1"
#18300
b100000000000 %
b100000000000 1
b1100 2
1.
1!
b10000000 -
1,
0"
#18350
0#
1"
#18400
0/
0!
b0 -
0+
0"
#18450
1#
1"
#18500
b1101 *
1'
0"
#18528
b1110 &
b1110 (
b1110 )
#18550
0#
1"
#18600
0.
1!
b1 -
1+
0"
#18650
1#
1"
#18700
1/
0!
b10 -
0,
0"
#18750
0#
1"
#18800
1!
0'
b100 -
1,
0"
#18850
b10 0
1#
1"
#18900
0"
#18950
0#
1"
#19000
b1000 -
0"
#19050
b100 0
1#
1"
#19100
0"
#19150
0#
1"
#19200
0!
b10000 -
0,
0"
#19250
b1000 0
1#
1"
#19300
0"
#19350
0#
1"
#19400
1!
b100000 -
1,
0"
#19450
b1101 3
b10000 0
1#
1"
#19500
0"
#19550
0#
1"
#19600
0!
b1000000 -
0,
0"
#19650
b1 0
1#
1"
#19700
b1000000000000 %
b1000000000000 1
b1101 2
1.
1!
b10000000 -
1,
0"
#19750
0#
1"
#19800
0/
0!
b0 -
0+
0"
#19850
1#
1"
#19900
b1110 *
1'
0"
#19928
b1111 &
b1111 (
b1111 )
#19950
0#
1"
#20000
0.
1!
b1 -
1+
0"
#20050
1#
1"
#20100
1/
0!
b10 -
0,
0"
#20150
0#
1"
#20200
1!
0'
b100 -
1,
0"
#20250
b10 0
1#
1"
#20300
0"
#20350
0#
1"
#20400
b1000 -
0"
#20450
b100 0
1#
1"
#20500
0"
#20550
0#
1"
#20600
b10000 -
0"
#20650
b1111 3
b1000 0
1#
1"
#20700
0"
#20750
0#
1"
#20800
0!
b100000 -
0,
0"
#20850
b1110 3
b10000 0
1#
1"
#20900
0"
#20950
0#
1"
#21000
b1000000 -
0"
#21050
b1 0
1#
1"
#21100
b10000000000000 %
b10000000000000 1
b1110 2
1.
1!
b10000000 -
1,
0"
#21150
0#
1"
#21200
0/
0!
b0 -
0+
0"
#21250
1#
1"
#21300
b1111 *
1'
0"
#21328
b0 &
b0 (
b0 )
#21350
0#
1"
#21400
0.
1!
b1 -
1+
0"
#21450
1#
1"
#21500
1/
0!
b10 -
0,
0"
#21550
0#
1"
#21600
1!
0'
b100 -
1,
0"
#21650
b10 0
1#
1"
#21700
0"
#21750
0#
1"
#21800
b1000 -
0"
#21850
b100 0
1#
1"
#21900
0"
#21950
0#
1"
#22000
b10000 -
0"
#22050
b1000 0
1#
1"
#22100
0"
#22150
0#
1"
#22200
b100000 -
0"
#22250
b1111 3
b10000 0
1#
1"
#22300
0"
#22350
0#
1"
#22400
0!
b1000000 -
0,
0"
#22450
b1 0
1#
1"
#22500
b100000000000000 %
b100000000000000 1
b1111 2
1.
1!
b10000000 -
1,
0"
#22550
0#
1"
#22600
0/
0!
b0 -
0+
0"
#22650
1#
1"
#22700
b0 *
1'
0"
#22728
b1 &
b1 (
b1 )
#22750
0#
1"
#22800
0.
1!
b1 -
1+
0"
#22850
1#
1"
#22900
1/
0!
b10 -
0,
0"
#22950
0#
1"
#23000
0'
b100 -
0"
#23050
b111 3
b10 0
1#
1"
#23100
0"
#23150
0#
1"
#23200
b1000 -
0"
#23250
b11 3
b100 0
1#
1"
#23300
0"
#23350
0#
1"
#23400
b10000 -
0"
#23450
b1 3
b1000 0
1#
1"
#23500
0"
#23550
0#
1"
#23600
b100000 -
0"
#23650
b0 3
b10000 0
1#
1"
#23700
0"
#23750
0#
1"
#23800
b1000000 -
0"
#23850
b1 0
1#
1"
#23900
b1000000000000000 %
b1000000000000000 1
b0 2
1.
1!
b10000000 -
1,
0"
#23950
0#
1"
#24000
0/
0!
b0 -
0+
0"
#24050
1#
1"
#24100
b1 *
1'
0"
#24128
b10 &
b10 (
b10 )
#24150
0#
1"
#24200
0.
1!
b1 -
1+
0"
#24250
1#
1"
#24300
1/
0!
b10 -
0,
0"
#24350
0#
1"
#24400
0'
b100 -
0"
#24450
b10 0
1#
1"
#24500
0"
#24550
0#
1"
#24600
b1000 -
0"
#24650
b100 0
1#
1"
#24700
0"
#24750
0#
1"
#24800
b10000 -
0"
#24850
b1000 0
1#
1"
#24900
0"
#24950
0#
1"
#25000
1!
b100000 -
1,
0"
#25050
b1 3
b10000 0
1#
1"
#25100
0"
#25150
0#
1"
#25200
0!
b1000000 -
0,
0"
#25250
b1 0
1#
1"
#25300
b1 %
b1 1
b1 2
1.
1!
b10000000 -
1,
0"
#25350
0#
1"
#25400
0/
0!
b0 -
0+
0"
#25450
1#
1"
#25500
b10 *
1'
0"
#25528
b11 &
b11 (
b11 )
#25550
0#
1"
#25600
0.
1!
b1 -
1+
0"
#25650
1#
1"
#25700
1/
0!
b10 -
0,
0"
#25750
0#
1"
#25800
0'
b100 -
0"
#25850
b10 0
1#
1"
#25900
0"
#25950
0#
1"
#26000
b1000 -
0"
#26050
b100 0
1#
1"
#26100
0"
#26150
0#
1"
#26200
1!
b10000 -
1,
0"
#26250
b11 3
b1000 0
1#
1"
#26300
0"
#26350
0#
1"
#26400
0!
b100000 -
0,
0"
#26450
b10 3
b10000 0
1#
1"
#26500
0"
#26550
0#
1"
#26600
b1000000 -
0"
#26650
b1 0
1#
1"
#26700
b10 %
b10 1
b10 2
1.
1!
b10000000 -
1,
0"
#26750
0#
1"
#26800
0/
0!
b0 -
0+
0"
#26850
1#
1"
#26900
b11 *
1'
0"
#26928
b100 &
b100 (
b100 )
#26950
0#
1"
#27000
0.
1!
b1 -
1+
0"
#27050
1#
1"
#27100
1/
0!
b10 -
0,
0"
#27150
0#
1"
#27200
0'
b100 -
0"
#27250
b10 0
1#
1"
#27300
0"
#27350
0#
1"
#27400
b1000 -
0"
#27450
b100 0
1#
1"
#27500
0"
#27550
0#
1"
#27600
1!
b10000 -
1,
0"
#27650
b1000 0
1#
1"
#27700
0"
#27750
0#
1"
#27800
b100000 -
0"
#27850
b11 3
b10000 0
1#
1"
#27900
0"
#27950
0#
1"
#28000
0!
b1000000 -
0,
0"
#28050
b1 0
1#
1"
#28100
b100 %
b100 1
b11 2
1.
1!
b10000000 -
1,
0"
#28150
0#
1"
#28200
0/
0!
b0 -
0+
0"
#28250
1#
1"
#28300
b100 *
1'
0"
#28328
b101 &
b101 (
b101 )
#28350
0#
1"
#28400
0.
1!
b1 -
1+
0"
#28450
1#
1"
#28500
1/
0!
b10 -
0,
0"
#28550
0#
1"
#28600
0'
b100 -
0"
#28650
b10 0
1#
1"
#28700
0"
#28750
0#
1"
#28800
1!
b1000 -
1,
0"
#28850
b111 3
b100 0
1#
1"
#28900
0"
#28950
0#
1"
#29000
0!
b10000 -
0,
0"
#29050
b101 3
b1000 0
1#
1"
#29100
0"
#29150
0#
1"
#29200
b100000 -
0"
#29250
b100 3
b10000 0
1#
1"
#29300
0"
#29350
0#
1"
#29400
b1000000 -
0"
#29450
b1 0
1#
1"
#29500
b1000 %
b1000 1
b100 2
1.
1!
b10000000 -
1,
0"
#29550
0#
1"
#29600
0/
0!
b0 -
0+
0"
#29650
1#
1"
#29700
b101 *
1'
0"
#29728
b110 &
b110 (
b110 )
#29750
0#
1"
#29800
0.
1!
b1 -
1+
0"
#29850
1#
1"
#29900
1/
0!
b10 -
0,
0"
#29950
0#
1"
#30000
0'
b100 -
0"
#30050
b10 0
1#
1"
#30100
0"
#30150
0#
1"
#30200
1!
b1000 -
1,
0"
#30250
b100 0
1#
1"
#30300
0"
#30350
0#
1"
#30400
0!
b10000 -
0,
0"
#30450
b1000 0
1#
1"
#30500
0"
#30550
0#
1"
#30600
1!
b100000 -
1,
0"
#30650
b101 3
b10000 0
1#
1"
#30700
0"
#30750
0#
1"
#30800
0!
b1000000 -
0,
0"
#30850
b1 0
1#
1"
#30900
b10000 %
b10000 1
b101 2
1.
1!
b10000000 -
1,
0"
#30950
0#
1"
#31000
0/
0!
b0 -
0+
0"
#31050
1#
1"
#31100
b110 *
1'
0"
#31128
b111 &
b111 (
b111 )
#31150
0#
1"
#31200
0.
1!
b1 -
1+
0"
#31250
1#
1"
#31300
1/
0!
b10 -
0,
0"
#31350
0#
1"
#31400
0'
b100 -
0"
#31450
b10 0
1#
1"
#31500
0"
#31550
0#
1"
#31600
1!
b1000 -
1,
0"
#31650
b100 0
1#
1"
#31700
0"
#31750
0#
1"
#31800
b10000 -
0"
#31850
b111 3
b1000 0
1#
1"
#31900
0"
#31950
0#
1"
#32000
0!
b100000 -
0,
0"
#32050
b110 3
b10000 0
1#
1"
#32100
0"
#32150
0#
1"
#32200
b1000000 -
0"
#32250
b1 0
1#
1"
#32300
b100000 %
b100000 1
b110 2
1.
1!
b10000000 -
1,
0"
#32350
0#
1"
#32400
0/
0!
b0 -
0+
0"
#32450
1#
1"
#32500
b111 *
1'
0"
#32528
b1000 &
b1000 (
b1000 )
#32550
0#
1"
#32600
0.
1!
b1 -
1+
0"
#32650
1#
1"
#32700
1/
0!
b10 -
0,
0"
#32750
0#
1"
#32800
0'
b100 -
0"
#32850
b10 0
1#
1"
#32900
0"
#32950
0#
1"
#33000
1!
b1000 -
1,
0"
#33050
b100 0
1#
1"
#33100
0"
#33150
0#
1"
#33200
b10000 -
0"
#33250
b1000 0
1#
1"
#33300
0"
#33350
0#
1"
#33400
b100000 -
0"
#33450
b111 3
b10000 0
1#
1"
#33500
0"
#33550
0#
1"
#33600
0!
b1000000 -
0,
0"
#33650
b1 0
1#
1"
#33700
b1000000 %
b1000000 1
b111 2
1.
1!
b10000000 -
1,
0"
#33750
0#
1"
#33800
0/
0!
b0 -
0+
0"
#33850
1#
1"
#33900
b1000 *
1'
0"
#33928
b1001 &
b1001 (
b1001 )
#33950
0#
1"
#34000
0.
1!
b1 -
1+
0"
#34050
1#
1"
#34100
1/
0!
b10 -
0,
0"
#34150
0#
1"
#34200
1!
0'
b100 -
1,
0"
#34250
b1111 3
b10 0
1#
1"
#34300
0"
#34350
0#
1"
#34400
0!
b1000 -
0,
0"
#34450
b1011 3
b100 0
1#
1"
#34500
0"
#34550
0#
1"
#34600
b10000 -
0"
#34650
b1001 3
b1000 0
1#
1"
#34700
0"
#34750
0#
1"
#34800
b100000 -
0"
#34850
b1000 3
b10000 0
1#
1"
#34900
0"
#34950
0#
1"
#35000
b1000000 -
0"
#35050
b1 0
1#
1"
#35100
b10000000 %
b10000000 1
b1000 2
1.
1!
b10000000 -
1,
0"
#35150
0#
1"
#35200
0/
0!
b0 -
0+
0"
#35250
1#
1"
#35300
b1001 *
1'
0"
#35328
b1010 &
b1010 (
b1010 )
#35350
0#
1"
#35400
0.
1!
b1 -
1+
0"
#35450
1#
1"
#35500
1/
0!
b10 -
0,
0"
#35550
0#
1"
#35600
1!
0'
b100 -
1,
0"
#35650
b10 0
1#
1"
#35700
0"
#35750
0#
1"
#35800
0!
b1000 -
0,
0"
#35850
b100 0
1#
1"
#35900
0"
#35950
0#
1"
#36000
b10000 -
0"
#36050
b1000 0
1#
1"
#36100
0"
#36150
0#
1"
#36200
1!
b100000 -
1,
0"
#36250
b1001 3
b10000 0
1#
1"
#36300
0"
#36350
0#
1"
#36400
0!
b1000000 -
0,
0"
#36450
b1 0
1#
1"
#36500
b100000000 %
b100000000 1
b1001 2
1.
1!
b10000000 -
1,
0"
#36550
0#
1"
#36600
0/
0!
b0 -
0+
0"
#36650
1#
1"
#36700
b1010 *
1'
0"
#36728
b1011 &
b1011 (
b1011 )
#36750
0#
1"
#36800
0.
1!
b1 -
1+
0"
#36850
1#
1"
#36900
1/
0!
b10 -
0,
0"
#36950
0#
1"
#37000
1!
0'
b100 -
1,
0"
#37050
b10 0
1#
1"
#37100
0"
#37150
0#
1"
#37200
0!
b1000 -
0,
0"
#37250
b100 0
1#
1"
#37300
0"
#37350
0#
1"
#37400
1!
b10000 -
1,
0"
#37450
b1011 3
b1000 0
1#
1"
#37500
0"
#37550
0#
1"
#37600
0!
b100000 -
0,
0"
#37650
b1010 3
b10000 0
1#
1"
#37700
0"
#37750
0#
1"
#37800
b1000000 -
0"
#37850
b1 0
1#
1"
#37900
b1000000000 %
b1000000000 1
b1010 2
1.
1!
b10000000 -
1,
0"
#37950
0#
1"
#38000
0/
0!
b0 -
0+
0"
#38050
1#
1"
#38100
b1011 *
1'
0"
#38128
b1100 &
b1100 (
b1100 )
#38150
0#
1"
#38200
0.
1!
b1 -
1+
0"
#38250
1#
1"
#38300
1/
0!
b10 -
0,
0"
#38350
0#
1"
#38400
1!
0'
b100 -
1,
0"
#38450
b10 0
1#
1"
#38500
0"
#38550
0#
1"
#38600
0!
b1000 -
0,
0"
#38650
b100 0
1#
1"
#38700
0"
#38750
0#
1"
#38800
1!
b10000 -
1,
0"
#38850
b1000 0
1#
1"
#38900
0"
#38950
0#
1"
#39000
b100000 -
0"
#39050
b1011 3
b10000 0
1#
1"
#39100
0"
#39150
0#
1"
#39200
0!
b1000000 -
0,
0"
#39250
b1 0
1#
1"
#39300
b10000000000 %
b10000000000 1
b1011 2
1.
1!
b10000000 -
1,
0"
#39350
0#
1"
#39400
0/
0!
b0 -
0+
0"
#39450
1#
1"
#39500
b1100 *
1'
0"
#39528
b1101 &
b1101 (
b1101 )
#39550
0#
1"
#39600
0.
1!
b1 -
1+
0"
#39650
1#
1"
#39700
1/
0!
b10 -
0,
0"
#39750
0#
1"
#39800
1!
0'
b100 -
1,
0"
#39850
b10 0
1#
1"
#39900
0"
#39950
0#
1"
#40000
b1000 -
0"
#40050
b1111 3
b100 0
1#
1"
#40100
0"
#40150
0#
1"
#40200
0!
b10000 -
0,
0"
#40250
b1101 3
b1000 0
1#
1"
#40300
0"
#40350
0#
1"
#40400
b100000 -
0"
#40450
b1100 3
b10000 0
1#
1"
#40500
0"
#40550
0#
1"
#40600
b1000000 -
0"
#40650
b1 0
1#
1"
#40700
b100000000000 %
b100000000000 1
b1100 2
1.
1!
b10000000 -
1,
0"
#40750
0#
1"
#40800
0/
0!
b0 -
0+
0"
#40850
1#
1"
#40900
b1101 *
1'
0"
#40928
b1110 &
b1110 (
b1110 )
#40950
0#
1"
#41000
0.
1!
b1 -
1+
0"
#41050
1#
1"
#41100
1/
0!
b10 -
0,
0"
#41150
0#
1"
#41200
1!
0'
b100 -
1,
0"
#41250
b10 0
1#
1"
#41300
0"
#41350
0#
1"
#41400
b1000 -
0"
#41450
b100 0
1#
1"
#41500
0"
#41550
0#
1"
#41600
0!
b10000 -
0,
0"
#41650
b1000 0
1#
1"
#41700
0"
#41750
0#
1"
#41800
1!
b100000 -
1,
0"
#41850
b1101 3
b10000 0
1#
1"
#41900
0"
#41950
0#
1"
#42000
0!
b1000000 -
0,
0"
#42050
b1 0
1#
1"
#42100
b1000000000000 %
b1000000000000 1
b1101 2
1.
1!
b10000000 -
1,
0"
#42150
0#
1"
#42200
0/
0!
b0 -
0+
0"
#42250
1#
1"
#42300
b1110 *
1'
0"
#42328
b1111 &
b1111 (
b1111 )
#42350
0#
1"
#42400
0.
1!
b1 -
1+
0"
#42450
1#
1"
#42500
1/
0!
b10 -
0,
0"
#42550
0#
1"
#42600
1!
0'
b100 -
1,
0"
#42650
b10 0
1#
1"
#42700
0"
#42750
0#
1"
#42800
b1000 -
0"
#42850
b100 0
1#
1"
#42900
0"
#42950
0#
1"
#43000
b10000 -
0"
#43050
b1111 3
b1000 0
1#
1"
#43100
0"
#43150
0#
1"
#43200
0!
b100000 -
0,
0"
#43250
b1110 3
b10000 0
1#
1"
#43300
0"
#43350
0#
1"
#43400
b1000000 -
0"
#43450
b1 0
1#
1"
#43500
b10000000000000 %
b10000000000000 1
b1110 2
1.
1!
b10000000 -
1,
0"
#43550
0#
1"
#43600
0/
0!
b0 -
0+
0"
#43650
1#
1"
#43700
b1111 *
1'
0"
#43728
b0 &
b0 (
b0 )
#43750
0#
1"
#43800
0.
1!
b1 -
1+
0"
